Workbook
Name Data_Consolidado: Table2[#All]
Name Slicer_Apt: #N/A

Sheet INCOME
A1: Check-in Date | B1: Check-out Date | C1: Num_Nights | D1: APARTMENT | E1: NAME | F1: FULL AMOUNT usd | G1: FULL AMOUNT mxn pesos | H1: 20% commission | I1: RENTAL PLATFORM | J1: Month
A2: 44635 | B2: 44638 | C2: =Table1[[#This Row],[Check-out Date]]-Table1[[#This Row],[Check-in Date]] -> 3 | D2: B303 | E2: Emmeline Page | F2: 336.29 | G2: =Table1[[#This Row],[FULL AMOUNT usd]]*20 -> 6725.8 | H2: =F2*0.2 -> 67.258 | I2: Airbnb | J2: =YEAR(A2)&"-"&TEXT(MONTH(A2),"00") -> 2022-03
A3: 44635 | B3: 44640 | C3: =Table1[[#This Row],[Check-out Date]]-Table1[[#This Row],[Check-in Date]] -> 5 | D3: A302 | E3: Spencer Lanier | F3: 533.36 | G3: =Table1[[#This Row],[FULL AMOUNT usd]]*20 -> 10667.2 | H3: =F3*0.2 -> 106.672 | I3: Airbnb | J3: =YEAR(A3)&"-"&TEXT(MONTH(A3),"00") -> 2022-03
A4: 44638 | B4: 44656 | C4: =Table1[[#This Row],[Check-out Date]]-Table1[[#This Row],[Check-in Date]] -> 18 | D4: B303 | E4: Emmeline Page | F4: 1298 | G4: =Table1[[#This Row],[FULL AMOUNT usd]]*20 -> 25960 | H4: =F4*0.2 -> 259.6 | I4: Airbnb | J4: =YEAR(A4)&"-"&TEXT(MONTH(A4),"00") -> 2022-03
A5: 44644 | B5: 44660 | C5: =Table1[[#This Row],[Check-out Date]]-Table1[[#This Row],[Check-in Date]] -> 16 | D5: A302 | E5: Stephen Mack | F5: 857.89 | G5: =Table1[[#This Row],[FULL AMOUNT usd]]*20 -> 17157.8 | H5: =F5*0.2 -> 171.578 | I5: Airbnb | J5: =YEAR(A5)&"-"&TEXT(MONTH(A5),"00") -> 2022-03
A6: 44645 | B6: 44647 | C6: =Table1[[#This Row],[Check-out Date]]-Table1[[#This Row],[Check-in Date]] -> 2 | D6: A302 | E6: Jhonatham Cummings | F6: 291.54 | G6: =Table1[[#This Row],[FULL AMOUNT usd]]*20 -> 5830.8 | H6: =F6*0.2 -> 58.308 | I6: Airbnb | J6: =YEAR(A6)&"-"&TEXT(MONTH(A6),"00") -> 2022-03
A7: 44652 | B7: 44656 | C7: =Table1[[#This Row],[Check-out Date]]-Table1[[#This Row],[Check-in Date]] -> 4 | D7: A302 | E7: Ian Downie | F7: 448 | G7: =Table1[[#This Row],[FULL AMOUNT usd]]*20 -> 8960 | H7: =F7*0.2 -> 89.6 | I7: Booking | J7: =YEAR(A7)&"-"&TEXT(MONTH(A7),"00") -> 2022-04
A8: 44659 | B8: 44661 | C8: =Table1[[#This Row],[Check-out Date]]-Table1[[#This Row],[Check-in Date]] -> 2 | D8: B303 | E8: Ryan Walsh | F8: 268.94 | G8: =Table1[[#This Row],[FULL AMOUNT usd]]*20 -> 5378.8 | H8: =F8*0.2 -> 53.788 | I8: Airbnb | J8: =YEAR(A8)&"-"&TEXT(MONTH(A8),"00") -> 2022-04
A9: 44661 | B9: 44666 | C9: =Table1[[#This Row],[Check-out Date]]-Table1[[#This Row],[Check-in Date]] -> 5 | D9: A302 | E9: Misty Erkkila | F9: 627.15 | G9: =Table1[[#This Row],[FULL AMOUNT usd]]*20 -> 12543 | H9: =F9*0.2 -> 125.43 | I9: Airbnb | J9: =YEAR(A9)&"-"&TEXT(MONTH(A9),"00") -> 2022-04
A10: 44664 | B10: 44667 | C10: =Table1[[#This Row],[Check-out Date]]-Table1[[#This Row],[Check-in Date]] -> 3 | D10: B303 | E10: Taran Parmar | F10: 335.61 | G10: =Table1[[#This Row],[FULL AMOUNT usd]]*20 -> 6712.2 | H10: =F10*0.2 -> 67.122 | I10: Airbnb | J10: =YEAR(A10)&"-"&TEXT(MONTH(A10),"00") -> 2022-04
A11: 44667 | B11: 44670 | C11: =Table1[[#This Row],[Check-out Date]]-Table1[[#This Row],[Check-in Date]] -> 3 | D11: A302 | E11: Taran Parmar | F11: 360 | G11: =Table1[[#This Row],[FULL AMOUNT usd]]*20 -> 7200 | H11: =F11*0.2 -> 72 | I11: Airbnb | J11: =YEAR(A11)&"-"&TEXT(MONTH(A11),"00") -> 2022-04
A12: 44668 | B12: 44681 | C12: =Table1[[#This Row],[Check-out Date]]-Table1[[#This Row],[Check-in Date]] -> 13 | D12: B303 | E12: Sergey Kulagin | F12: 1449.39 | G12: =Table1[[#This Row],[FULL AMOUNT usd]]*20 -> 28987.8 | H12: =F12*0.2 -> 289.878 | I12: Airbnb | J12: =YEAR(A12)&"-"&TEXT(MONTH(A12),"00") -> 2022-04
A13: 44673 | B13: 44680 | C13: =Table1[[#This Row],[Check-out Date]]-Table1[[#This Row],[Check-in Date]] -> 7 | D13: A302 | E13: Hilary Hoover | F13: 996.66 | G13: =Table1[[#This Row],[FULL AMOUNT usd]]*20 -> 19933.2 | H13: =F13*0.2 -> 199.332 | I13: Airbnb | J13: =YEAR(A13)&"-"&TEXT(MONTH(A13),"00") -> 2022-04
... A34: 44786 | B34: 44790 | C34: =Table1[[#This Row],[Check-out Date]]-Table1[[#This Row],[Check-in Date]] -> 4 | D34: A302 | E34: Nikia Leamire | F34: 452.11 | G34: =Table1[[#This Row],[FULL AMOUNT usd]]*20 -> 9042.2 | H34: =F34*0.2 -> 90.422 | I34: Airbnb | J34: =YEAR(A34)&"-"&TEXT(MONTH(A34),"00") -> 2022-08
A35: 44789 | B35: 44796 | C35: =Table1[[#This Row],[Check-out Date]]-Table1[[#This Row],[Check-in Date]] -> 7 | D35: C301 | F35: 631.62 | G35: =Table1[[#This Row],[FULL AMOUNT usd]]*20 -> 12632.4 | H35: =F35*0.2 -> 126.324 | I35: Airbnb | J35: =YEAR(A35)&"-"&TEXT(MONTH(A35),"00") -> 2022-08
A36: 44797 | B36: 44802 | C36: =Table1[[#This Row],[Check-out Date]]-Table1[[#This Row],[Check-in Date]] -> 5 | D36: C301 | E36: Alexis Dubourdieu | F36: 171.42 | G36: =Table1[[#This Row],[FULL AMOUNT usd]]*20 -> 3428.4 | H36: =F36*0.2 -> 34.284 | I36: Direct Reservation | J36: =YEAR(A36)&"-"&TEXT(MONTH(A36),"00") -> 2022-08
A37: 44797 | B37: 44802 | C37: =Table1[[#This Row],[Check-out Date]]-Table1[[#This Row],[Check-in Date]] -> 5 | D37: C301 | F37: 171.42 | G37: =Table1[[#This Row],[FULL AMOUNT usd]]*20 -> 3428.4 | H37: =F37*0.2 -> 34.284 | I37: Airbnb | J37: =YEAR(A37)&"-"&TEXT(MONTH(A37),"00") -> 2022-08
A38: 44798 | B38: 44803 | C38: =Table1[[#This Row],[Check-out Date]]-Table1[[#This Row],[Check-in Date]] -> 5 | D38: B303 | E38: Matthew Tatum | F38: 269.51 | G38: =Table1[[#This Row],[FULL AMOUNT usd]]*20 -> 5390.2 | H38: =F38*0.2 -> 53.902 | I38: Airbnb | J38: =YEAR(A38)&"-"&TEXT(MONTH(A38),"00") -> 2022-08
A39: 44842 | B39: 44846 | C39: =Table1[[#This Row],[Check-out Date]]-Table1[[#This Row],[Check-in Date]] -> 4 | D39: A302 | E39: Greg Chapple | F39: 222 | G39: =Table1[[#This Row],[FULL AMOUNT usd]]*20 -> 4440 | H39: =F39*0.2 -> 44.4 | I39: Expedia | J39: =YEAR(A39)&"-"&TEXT(MONTH(A39),"00") -> 2022-10
A40: 44852 | B40: 44855 | C40: =Table1[[#This Row],[Check-out Date]]-Table1[[#This Row],[Check-in Date]] -> 3 | D40: A302 | E40: Jennifer Myers | F40: 321 | G40: =Table1[[#This Row],[FULL AMOUNT usd]]*20 -> 6420 | H40: =F40*0.2 -> 64.2 | I40: Airbnb | J40: =YEAR(A40)&"-"&TEXT(MONTH(A40),"00") -> 2022-10
A41: 44864 | B41: 44867 | C41: =Table1[[#This Row],[Check-out Date]]-Table1[[#This Row],[Check-in Date]] -> 3 | D41: A302 | E41: George White | F41: 357 | G41: =Table1[[#This Row],[FULL AMOUNT usd]]*20 -> 7140 | H41: =F41*0.2 -> 71.4 | I41: Airbnb | J41: =YEAR(A41)&"-"&TEXT(MONTH(A41),"00") -> 2022-10
A42: 44868 | B42: 44876 | C42: =Table1[[#This Row],[Check-out Date]]-Table1[[#This Row],[Check-in Date]] -> 8 | D42: A302 | E42: Yadira Barrera | F42: 918 | G42: =Table1[[#This Row],[FULL AMOUNT usd]]*20 -> 18360 | H42: =F42*0.2 -> 183.6 | I42: Airbnb | J42: =YEAR(A42)&"-"&TEXT(MONTH(A42),"00") -> 2022-11
A43: 44873 | B43: 44877 | C43: =Table1[[#This Row],[Check-out Date]]-Table1[[#This Row],[Check-in Date]] -> 4 | D43: C301 | E43: Cossette Haddock | F43: 291.54 | G43: =Table1[[#This Row],[FULL AMOUNT usd]]*20 -> 5830.8 | H43: =F43*0.2 -> 58.308 | I43: Expedia | J43: =YEAR(A43)&"-"&TEXT(MONTH(A43),"00") -> 2022-11
A44: 44873 | B44: 44877 | C44: =Table1[[#This Row],[Check-out Date]]-Table1[[#This Row],[Check-in Date]] -> 4 | D44: C301 | F44: 291.54 | G44: =Table1[[#This Row],[FULL AMOUNT usd]]*20 -> 5830.8 | H44: =F44*0.2 -> 58.308 | I44: Airbnb | J44: =YEAR(A44)&"-"&TEXT(MONTH(A44),"00") -> 2022-11
A45: 44876 | B45: 44881 | C45: =Table1[[#This Row],[Check-out Date]]-Table1[[#This Row],[Check-in Date]] -> 5 | D45: A302 | E45: Johnny Hernandez | F45: 621.5 | G45: =Table1[[#This Row],[FULL AMOUNT usd]]*20 -> 12430 | H45: =F45*0.2 -> 124.3 | I45: Airbnb | J45: =YEAR(A45)&"-"&TEXT(MONTH(A45),"00") -> 2022-11
A46: 44878 | B46: 44884 | C46: =Table1[[#This Row],[Check-out Date]]-Table1[[#This Row],[Check-in Date]] -> 6 | D46: B303 | E46: Aniket Sharma | F46: 615 | G46: =Table1[[#This Row],[FULL AMOUNT usd]]*20 -> 12300 | H46: =F46*0.2 -> 123 | I46: Airbnb | J46: =YEAR(A46)&"-"&TEXT(MONTH(A46),"00") -> 2022-11
A47: 44885 | B47: 44889 | C47: =Table1[[#This Row],[Check-out Date]]-Table1[[#This Row],[Check-in Date]] -> 4 | D47: A302 | E47: Shane Finkelstein | F47: 337.65 | G47: =Table1[[#This Row],[FULL AMOUNT usd]]*20 -> 6753 | H47: =F47*0.2 -> 67.53 | I47: Expedia | J47: =YEAR(A47)&"-"&TEXT(MONTH(A47),"00") -> 2022-11
A48: 44888 | B48: 44893 | C48: =Table1[[#This Row],[Check-out Date]]-Table1[[#This Row],[Check-in Date]] -> 5 | D48: A302 | E48: Pre Knechia | F48: 211 | G48: =Table1[[#This Row],[FULL AMOUNT usd]]*20 -> 4220 | H48: =F48*0.2 -> 42.2 | I48: Expedia | J48: =YEAR(A48)&"-"&TEXT(MONTH(A48),"00") -> 2022-11
A49: 44895 | B49: 44899 | C49: =Table1[[#This Row],[Check-out Date]]-Table1[[#This Row],[Check-in Date]] -> 4 | D49: A302 | E49: Brian Concah | F49: 378.33 | G49: =Table1[[#This Row],[FULL AMOUNT usd]]*20 -> 7566.6 | H49: =F49*0.2 -> 75.666 | I49: Airbnb | J49: =YEAR(A49)&"-"&TEXT(MONTH(A49),"00") -> 2022-11
A50: 44898 | B50: 44902 | C50: =Table1[[#This Row],[Check-out Date]]-Table1[[#This Row],[Check-in Date]] -> 4 | D50: A302 | E50: Felix Bostel | F50: 258.55 | G50: =Table1[[#This Row],[FULL AMOUNT usd]]*20 -> 5171 | H50: =F50*0.2 -> 51.71 | I50: Expedia | J50: =YEAR(A50)&"-"&TEXT(MONTH(A50),"00") -> 2022-12
A51: 44899 | B51: 44903 | C51: =Table1[[#This Row],[Check-out Date]]-Table1[[#This Row],[Check-in Date]] -> 4 | D51: B303 | E51: Maya Dadez | F51: 378.33 | G51: =Table1[[#This Row],[FULL AMOUNT usd]]*20 -> 7566.6 | H51: =F51*0.2 -> 75.666 | I51: Expedia | J51: =YEAR(A51)&"-"&TEXT(MONTH(A51),"00") -> 2022-12
A52: 44903 | B52: 44906 | C52: =Table1[[#This Row],[Check-out Date]]-Table1[[#This Row],[Check-in Date]] -> 3 | D52: B303 | E52: Adrien Green | F52: 300.7 | G52: =Table1[[#This Row],[FULL AMOUNT usd]]*20 -> 6014 | H52: =F52*0.2 -> 60.14 | I52: Direct Reservation | J52: =YEAR(A52)&"-"&TEXT(MONTH(A52),"00") -> 2022-12
A53: 44915 | B53: 44920 | C53: =Table1[[#This Row],[Check-out Date]]-Table1[[#This Row],[Check-in Date]] -> 5 | D53: B303 | E53: Akshay Pimprikar | F53: 523.76 | G53: =Table1[[#This Row],[FULL AMOUNT usd]]*20 -> 10475.2 | H53: =F53*0.2 -> 104.752 | I53: Airbnb | J53: =YEAR(A53)&"-"&TEXT(MONTH(A53),"00") -> 2022-12
A54: 44916 | B54: 44920 | C54: =Table1[[#This Row],[Check-out Date]]-Table1[[#This Row],[Check-in Date]] -> 4 | D54: A302 | E54: Sameer Singh | F54: 272.11 | G54: =Table1[[#This Row],[FULL AMOUNT usd]]*20 -> 5442.2 | H54: =F54*0.2 -> 54.422 | I54: Airbnb | J54: =YEAR(A54)&"-"&TEXT(MONTH(A54),"00") -> 2022-12
A55: 44920 | B55: 44925 | C55: =Table1[[#This Row],[Check-out Date]]-Table1[[#This Row],[Check-in Date]] -> 5 | D55: A302 | E55: Karen G | F55: 1183.68 | G55: =Table1[[#This Row],[FULL AMOUNT usd]]*20 -> 23673.6 | H55: =F55*0.2 -> 236.736 | I55: Airbnb | J55: =YEAR(A55)&"-"&TEXT(MONTH(A55),"00") -> 2022-12
A56: 44920 | B56: 44922 | C56: =Table1[[#This Row],[Check-out Date]]-Table1[[#This Row],[Check-in Date]] -> 2 | D56: B303 | E56: Luis Lopez | F56: 472.02 | G56: =Table1[[#This Row],[FULL AMOUNT usd]]*20 -> 9440.4 | H56: =F56*0.2 -> 94.404 | I56: Airbnb | J56: =YEAR(A56)&"-"&TEXT(MONTH(A56),"00") -> 2022-12
... A58: 44923 | B58: 44925 | C58: =Table1[[#This Row],[Check-out Date]]-Table1[[#This Row],[Check-in Date]] -> 2 | D58: C301 | E58: Kerry Bole | F58: 110 | G58: =Table1[[#This Row],[FULL AMOUNT usd]]*20 -> 2200 | H58: =F58*0.2 -> 22 | I58: Airbnb | J58: =YEAR(A58)&"-"&TEXT(MONTH(A58),"00") -> 2022-12
A59: 44923 | B59: 44925 | C59: =Table1[[#This Row],[Check-out Date]]-Table1[[#This Row],[Check-in Date]] -> 2 | D59: C301 | F59: 160 | G59: =Table1[[#This Row],[FULL AMOUNT usd]]*20 -> 3200 | H59: =F59*0.2 -> 32 | I59: Airbnb | J59: =YEAR(A59)&"-"&TEXT(MONTH(A59),"00") -> 2022-12
A60: 44923 | B60: 44925 | C60: =Table1[[#This Row],[Check-out Date]]-Table1[[#This Row],[Check-in Date]] -> 2 | D60: C301 | F60: 110 | G60: =Table1[[#This Row],[FULL AMOUNT usd]]*20 -> 2200 | H60: =F60*0.2 -> 22 | I60: Airbnb | J60: =YEAR(A60)&"-"&TEXT(MONTH(A60),"00") -> 2022-12
A61: 44924 | B61: 44929 | C61: =Table1[[#This Row],[Check-out Date]]-Table1[[#This Row],[Check-in Date]] -> 5 | D61: B303 | E61: Jerrod Noble | F61: 2043.04 | G61: =Table1[[#This Row],[FULL AMOUNT usd]]*20 -> 40860.8 | H61: =F61*0.2 -> 408.608 | I61: Expedia | J61: =YEAR(A61)&"-"&TEXT(MONTH(A61),"00") -> 2022-12
A62: 44925 | B62: 44928 | C62: =Table1[[#This Row],[Check-out Date]]-Table1[[#This Row],[Check-in Date]] -> 3 | D62: A302 | E62: Dustin Spitzer | F62: 1128.99 | G62: =Table1[[#This Row],[FULL AMOUNT usd]]*20 -> 22579.8 | H62: =F62*0.2 -> 225.798 | I62: Expedia | J62: =YEAR(A62)&"-"&TEXT(MONTH(A62),"00") -> 2022-12
A63: 44925 | B63: 44957 | C63: =Table1[[#This Row],[Check-out Date]]-Table1[[#This Row],[Check-in Date]] -> 32 | D63: C301 | F63: 2500 | G63: =Table1[[#This Row],[FULL AMOUNT usd]]*20 -> 50000 | H63: =F63*0.2 -> 500 | I63: Airbnb | J63: =YEAR(A63)&"-"&TEXT(MONTH(A63),"00") -> 2022-12
A64: 44926 | B64: 44928 | C64: =Table1[[#This Row],[Check-out Date]]-Table1[[#This Row],[Check-in Date]] -> 2 | D64: C301 | F64: 170 | G64: =Table1[[#This Row],[FULL AMOUNT usd]]*20 -> 3400 | H64: =F64*0.2 -> 34 | I64: Airbnb | J64: =YEAR(A64)&"-"&TEXT(MONTH(A64),"00") -> 2022-12
A65: 44928 | B65: 44932 | C65: =Table1[[#This Row],[Check-out Date]]-Table1[[#This Row],[Check-in Date]] -> 4 | D65: C301 | E65: Raza Kanani | F65: 694.74 | G65: =Table1[[#This Row],[FULL AMOUNT usd]]*20 -> 13894.8 | H65: =F65*0.2 -> 138.948 | I65: Expedia | J65: =YEAR(A65)&"-"&TEXT(MONTH(A65),"00") -> 2023-01
A66: 44928 | B66: 44932 | C66: =Table1[[#This Row],[Check-out Date]]-Table1[[#This Row],[Check-in Date]] -> 4 | D66: C301 | F66: 694.74 | G66: =Table1[[#This Row],[FULL AMOUNT usd]]*20 -> 13894.8 | H66: =F66*0.2 -> 138.948 | I66: Airbnb | J66: =YEAR(A66)&"-"&TEXT(MONTH(A66),"00") -> 2023-01
A67: 44929 | B67: 44933 | C67: =Table1[[#This Row],[Check-out Date]]-Table1[[#This Row],[Check-in Date]] -> 4 | D67: A302 | E67: Gustavo Blascovi | F67: 785.13 | G67: =Table1[[#This Row],[FULL AMOUNT usd]]*20 -> 15702.6 | H67: =F67*0.2 -> 157.026 | I67: Direct Reservation | J67: =YEAR(A67)&"-"&TEXT(MONTH(A67),"00") -> 2023-01
A68: 44929 | B68: 44933 | C68: =Table1[[#This Row],[Check-out Date]]-Table1[[#This Row],[Check-in Date]] -> 4 | D68: A302 | E68: Beatrijs Berre | F68: 529.74 | G68: =Table1[[#This Row],[FULL AMOUNT usd]]*20 -> 10594.8 | H68: =F68*0.2 -> 105.948 | I68: Intima Reservation | J68: =YEAR(A68)&"-"&TEXT(MONTH(A68),"00") -> 2023-01
A69: 44931 | B69: 44934 | C69: =Table1[[#This Row],[Check-out Date]]-Table1[[#This Row],[Check-in Date]] -> 3 | D69: B303 | E69: Yael Vazquez | F69: 622.77 | G69: =Table1[[#This Row],[FULL AMOUNT usd]]*20 -> 12455.4 | H69: =F69*0.2 -> 124.554 | I69: Airbnb | J69: =YEAR(A69)&"-"&TEXT(MONTH(A69),"00") -> 2023-01
A70: 44933 | B70: 44940 | C70: =Table1[[#This Row],[Check-out Date]]-Table1[[#This Row],[Check-in Date]] -> 7 | D70: C301 | E70: Riccardo Coan | F70: 1120 | G70: =Table1[[#This Row],[FULL AMOUNT usd]]*20 -> 22400 | H70: =F70*0.2 -> 224 | I70: Intima Reservation | J70: =YEAR(A70)&"-"&TEXT(MONTH(A70),"00") -> 2023-01
A71: 44933 | B71: 44936 | C71: =Table1[[#This Row],[Check-out Date]]-Table1[[#This Row],[Check-in Date]] -> 3 | D71: A302 | E71: Kevin Dyal | F71: 908.97 | G71: =Table1[[#This Row],[FULL AMOUNT usd]]*20 -> 18179.4 | H71: =F71*0.2 -> 181.794 | I71: Expedia | J71: =YEAR(A71)&"-"&TEXT(MONTH(A71),"00") -> 2023-01
A72: 44933 | B72: 44940 | C72: =Table1[[#This Row],[Check-out Date]]-Table1[[#This Row],[Check-in Date]] -> 7 | D72: C301 | F72: 1120 | G72: =Table1[[#This Row],[FULL AMOUNT usd]]*20 -> 22400 | H72: =F72*0.2 -> 224 | I72: Airbnb | J72: =YEAR(A72)&"-"&TEXT(MONTH(A72),"00") -> 2023-01
A73: 44934 | B73: 44938 | C73: =Table1[[#This Row],[Check-out Date]]-Table1[[#This Row],[Check-in Date]] -> 4 | D73: B303 | E73: Aaron Boring | F73: 475.92 | G73: =Table1[[#This Row],[FULL AMOUNT usd]]*20 -> 9518.4 | H73: =F73*0.2 -> 95.184 | I73: Expedia | J73: =YEAR(A73)&"-"&TEXT(MONTH(A73),"00") -> 2023-01
A74: 44937 | B74: 44941 | C74: =Table1[[#This Row],[Check-out Date]]-Table1[[#This Row],[Check-in Date]] -> 4 | D74: A302 | E74: Didier Milleri | F74: 326.35 | G74: =Table1[[#This Row],[FULL AMOUNT usd]]*20 -> 6527 | H74: =F74*0.2 -> 65.27 | I74: Direct Reservation | J74: =YEAR(A74)&"-"&TEXT(MONTH(A74),"00") -> 2023-01
A75: 44938 | B75: 44944 | C75: =Table1[[#This Row],[Check-out Date]]-Table1[[#This Row],[Check-in Date]] -> 6 | D75: B303 | E75: Elree Paw | F75: 716.64 | G75: =Table1[[#This Row],[FULL AMOUNT usd]]*20 -> 14332.8 | H75: =F75*0.2 -> 143.328 | I75: Expedia | J75: =YEAR(A75)&"-"&TEXT(MONTH(A75),"00") -> 2023-01
A76: 44941 | B76: 44969 | C76: =Table1[[#This Row],[Check-out Date]]-Table1[[#This Row],[Check-in Date]] -> 28 | D76: A302 | E76: Emily LeVan | F76: 3835.63 | G76: =Table1[[#This Row],[FULL AMOUNT usd]]*20 -> 76712.6 | H76: =F76*0.2 -> 767.126 | I76: Direct Reservation | J76: =YEAR(A76)&"-"&TEXT(MONTH(A76),"00") -> 2023-01
A77: 44962 | B77: 44968 | C77: =Table1[[#This Row],[Check-out Date]]-Table1[[#This Row],[Check-in Date]] -> 6 | D77: B303 | E77: Rob Landsam | F77: 743 | G77: =Table1[[#This Row],[FULL AMOUNT usd]]*20 -> 14860 | H77: =F77*0.2 -> 148.6 | I77: Airbnb | J77: =YEAR(A77)&"-"&TEXT(MONTH(A77),"00") -> 2023-02
A78: 44962 | B78: 44968 | C78: =Table1[[#This Row],[Check-out Date]]-Table1[[#This Row],[Check-in Date]] -> 6 | D78: C301 | F78: 110 | G78: =Table1[[#This Row],[FULL AMOUNT usd]]*20 -> 2200 | H78: =F78*0.2 -> 22 | I78: Airbnb | J78: =YEAR(A78)&"-"&TEXT(MONTH(A78),"00") -> 2023-02
A79: 44965 | B79: 44968 | C79: =Table1[[#This Row],[Check-out Date]]-Table1[[#This Row],[Check-in Date]] -> 3 | D79: C301 | E79: Shuzao Yan | F79: 375.81 | G79: =Table1[[#This Row],[FULL AMOUNT usd]]*20 -> 7516.2 | H79: =F79*0.2 -> 75.162 | I79: Booking | J79: =YEAR(A79)&"-"&TEXT(MONTH(A79),"00") -> 2023-02
A80: 44965 | B80: 44968 | C80: =Table1[[#This Row],[Check-out Date]]-Table1[[#This Row],[Check-in Date]] -> 3 | D80: C301 | F80: 375.81 | G80: =Table1[[#This Row],[FULL AMOUNT usd]]*20 -> 7516.2 | H80: =F80*0.2 -> 75.162 | I80: Airbnb | J80: =YEAR(A80)&"-"&TEXT(MONTH(A80),"00") -> 2023-02
A81: 44967 | B81: 44974 | C81: =Table1[[#This Row],[Check-out Date]]-Table1[[#This Row],[Check-in Date]] -> 7 | D81: B303 | E81: Tamika Brighton | F81: 786 | G81: =Table1[[#This Row],[FULL AMOUNT usd]]*20 -> 15720 | H81: =F81*0.2 -> 157.2 | I81: Direct Reservation | J81: =YEAR(A81)&"-"&TEXT(MONTH(A81),"00") -> 2023-02
A82: 44968 | B82: 44971 | C82: =Table1[[#This Row],[Check-out Date]]-Table1[[#This Row],[Check-in Date]] -> 3 | D82: C301 | E82: Michael Limm | F82: 407 | G82: =Table1[[#This Row],[FULL AMOUNT usd]]*20 -> 8140 | H82: =F82*0.2 -> 81.4 | I82: Direct Reservation | J82: =YEAR(A82)&"-"&TEXT(MONTH(A82),"00") -> 2023-02
A83: 44968 | B83: 44971 | C83: =Table1[[#This Row],[Check-out Date]]-Table1[[#This Row],[Check-in Date]] -> 3 | D83: C301 | F83: 407 | G83: =Table1[[#This Row],[FULL AMOUNT usd]]*20 -> 8140 | H83: =F83*0.2 -> 81.4 | I83: Airbnb | J83: =YEAR(A83)&"-"&TEXT(MONTH(A83),"00") -> 2023-02
A84: 44968 | B84: 44972 | C84: =Table1[[#This Row],[Check-out Date]]-Table1[[#This Row],[Check-in Date]] -> 4 | D84: C301 | F84: 480 | G84: =Table1[[#This Row],[FULL AMOUNT usd]]*20 -> 9600 | H84: =F84*0.2 -> 96 | I84: Airbnb | J84: =YEAR(A84)&"-"&TEXT(MONTH(A84),"00") -> 2023-02
A85: 44971 | B85: 44976 | C85: =Table1[[#This Row],[Check-out Date]]-Table1[[#This Row],[Check-in Date]] -> 5 | D85: A302 | E85: Ryan Shaney | F85: 714 | G85: =Table1[[#This Row],[FULL AMOUNT usd]]*20 -> 14280 | H85: =F85*0.2 -> 142.8 | I85: Expedia | J85: =YEAR(A85)&"-"&TEXT(MONTH(A85),"00") -> 2023-02
A86: 44978 | B86: 44983 | C86: =Table1[[#This Row],[Check-out Date]]-Table1[[#This Row],[Check-in Date]] -> 5 | D86: C301 | E86: Kerry Bole | F86: 500 | G86: =Table1[[#This Row],[FULL AMOUNT usd]]*20 -> 10000 | H86: =F86*0.2 -> 100 | I86: Airbnb | J86: =YEAR(A86)&"-"&TEXT(MONTH(A86),"00") -> 2023-02
A87: 44978 | B87: 44983 | C87: =Table1[[#This Row],[Check-out Date]]-Table1[[#This Row],[Check-in Date]] -> 5 | D87: C301 | F87: 500 | G87: =Table1[[#This Row],[FULL AMOUNT usd]]*20 -> 10000 | H87: =F87*0.2 -> 100 | I87: Airbnb | J87: =YEAR(A87)&"-"&TEXT(MONTH(A87),"00") -> 2023-02
A88: 44979 | B88: 44984 | C88: =Table1[[#This Row],[Check-out Date]]-Table1[[#This Row],[Check-in Date]] -> 5 | D88: A302 | E88: Elisabeth Quinn | F88: 573.47 | G88: =Table1[[#This Row],[FULL AMOUNT usd]]*20 -> 11469.4 | H88: =F88*0.2 -> 114.694 | I88: Direct Reservation | J88: =YEAR(A88)&"-"&TEXT(MONTH(A88),"00") -> 2023-02
A89: 44982 | B89: 45006 | C89: =Table1[[#This Row],[Check-out Date]]-Table1[[#This Row],[Check-in Date]] -> 24 | D89: B303 | E89: Tiffane Golson | F89: 515.28 | G89: =Table1[[#This Row],[FULL AMOUNT usd]]*20 -> 10305.6 | H89: =F89*0.2 -> 103.056 | I89: Expedia | J89: =YEAR(A89)&"-"&TEXT(MONTH(A89),"00") -> 2023-02
A90: 44982 | B90: 45016 | C90: =Table1[[#This Row],[Check-out Date]]-Table1[[#This Row],[Check-in Date]] -> 34 | D90: A302 | E90: Tahire Edirisinghe | F90: 562.96 | G90: =Table1[[#This Row],[FULL AMOUNT usd]]*20 -> 11259.2 | H90: =F90*0.2 -> 112.592 | I90: Airbnb | J90: =YEAR(A90)&"-"&TEXT(MONTH(A90),"00") -> 2023-02
A91: 44985 | B91: 44988 | C91: =Table1[[#This Row],[Check-out Date]]-Table1[[#This Row],[Check-in Date]] -> 3 | D91: A302 | E91: Jeff Devoe | F91: 674.61 | G91: =Table1[[#This Row],[FULL AMOUNT usd]]*20 -> 13492.2 | H91: =F91*0.2 -> 134.922 | I91: Airbnb | J91: =YEAR(A91)&"-"&TEXT(MONTH(A91),"00") -> 2023-02
A92: 44988 | B92: 44991 | C92: =Table1[[#This Row],[Check-out Date]]-Table1[[#This Row],[Check-in Date]] -> 3 | D92: A302 | E92: Alexander Villlalobos | F92: 212.75 | G92: =Table1[[#This Row],[FULL AMOUNT usd]]*20 -> 4255 | H92: =F92*0.2 -> 42.55 | I92: Airbnb | J92: =YEAR(A92)&"-"&TEXT(MONTH(A92),"00") -> 2023-03
A93: 44988 | B93: 44992 | C93: =Table1[[#This Row],[Check-out Date]]-Table1[[#This Row],[Check-in Date]] -> 4 | D93: B303 | E93: Noah Morrison | F93: 473.25 | G93: =Table1[[#This Row],[FULL AMOUNT usd]]*20 -> 9465 | H93: =F93*0.2 -> 94.65 | I93: Airbnb | J93: =YEAR(A93)&"-"&TEXT(MONTH(A93),"00") -> 2023-03
A94: 44997 | B94: 45000 | C94: =Table1[[#This Row],[Check-out Date]]-Table1[[#This Row],[Check-in Date]] -> 3 | D94: C301 | E94: Jawanna Hardy | F94: 480 | G94: =Table1[[#This Row],[FULL AMOUNT usd]]*20 -> 9600 | H94: =F94*0.2 -> 96 | I94: Expedia | J94: =YEAR(A94)&"-"&TEXT(MONTH(A94),"00") -> 2023-03
A95: 44997 | B95: 45000 | C95: =Table1[[#This Row],[Check-out Date]]-Table1[[#This Row],[Check-in Date]] -> 3 | D95: C301 | E95: Jawanna Hardy | G95: =Table1[[#This Row],[FULL AMOUNT usd]]*20 -> 0 | H95: =F95*0.2 -> 0 | I95: Direct Reservation | J95: =YEAR(A95)&"-"&TEXT(MONTH(A95),"00") -> 2023-03
A96: 44997 | B96: 45000 | C96: =Table1[[#This Row],[Check-out Date]]-Table1[[#This Row],[Check-in Date]] -> 3 | D96: C301 | F96: 580 | G96: =Table1[[#This Row],[FULL AMOUNT usd]]*20 -> 11600 | H96: =F96*0.2 -> 116 | I96: Airbnb | J96: =YEAR(A96)&"-"&TEXT(MONTH(A96),"00") -> 2023-03
A97: 45010 | B97: 45014 | C97: =Table1[[#This Row],[Check-out Date]]-Table1[[#This Row],[Check-in Date]] -> 4 | D97: A302 | E97: Ethan Glickstein | F97: 477 | G97: =Table1[[#This Row],[FULL AMOUNT usd]]*20 -> 9540 | H97: =F97*0.2 -> 95.4 | I97: Direct Reservation | J97: =YEAR(A97)&"-"&TEXT(MONTH(A97),"00") -> 2023-03
A98: 45015 | B98: 45025 | C98: =Table1[[#This Row],[Check-out Date]]-Table1[[#This Row],[Check-in Date]] -> 10 | D98: A302 | E98: Dominic Cashman | F98: 1046 | G98: =Table1[[#This Row],[FULL AMOUNT usd]]*20 -> 20920 | H98: =F98*0.2 -> 209.2 | I98: Expedia | J98: =YEAR(A98)&"-"&TEXT(MONTH(A98),"00") -> 2023-03
A99: 45017 | B99: 45022 | C99: =Table1[[#This Row],[Check-out Date]]-Table1[[#This Row],[Check-in Date]] -> 5 | D99: C301 | E99: Ken Komatsuda | F99: 580 | G99: =Table1[[#This Row],[FULL AMOUNT usd]]*20 -> 11600 | H99: =F99*0.2 -> 116 | I99: Expedia | J99: =YEAR(A99)&"-"&TEXT(MONTH(A99),"00") -> 2023-04
A100: 45017 | B100: 45022 | C100: =Table1[[#This Row],[Check-out Date]]-Table1[[#This Row],[Check-in Date]] -> 5 | D100: C301 | F100: 662.18 | G100: =Table1[[#This Row],[FULL AMOUNT usd]]*20 -> 13243.6 | H100: =F100*0.2 -> 132.436 | I100: Airbnb | J100: =YEAR(A100)&"-"&TEXT(MONTH(A100),"00") -> 2023-04
A101: 45018 | B101: 45025 | C101: =Table1[[#This Row],[Check-out Date]]-Table1[[#This Row],[Check-in Date]] -> 7 | D101: A302 | E101: Eoin K Cunneen | F101: 1036.76 | G101: =Table1[[#This Row],[FULL AMOUNT usd]]*20 -> 20735.2 | H101: =F101*0.2 -> 207.352 | I101: Expedia | J101: =YEAR(A101)&"-"&TEXT(MONTH(A101),"00") -> 2023-04
A102: 45023 | B102: 45027 | C102: =Table1[[#This Row],[Check-out Date]]-Table1[[#This Row],[Check-in Date]] -> 4 | D102: C301 | E102: Kai Naly Kelly | F102: 662.18 | G102: =Table1[[#This Row],[FULL AMOUNT usd]]*20 -> 13243.6 | H102: =F102*0.2 -> 132.436 | I102: Direct Reservation | J102: =YEAR(A102)&"-"&TEXT(MONTH(A102),"00") -> 2023-04
A103: 45023 | B103: 45027 | C103: =Table1[[#This Row],[Check-out Date]]-Table1[[#This Row],[Check-in Date]] -> 4 | D103: C301 | F103: 525 | G103: =Table1[[#This Row],[FULL AMOUNT usd]]*20 -> 10500 | H103: =F103*0.2 -> 105 | I103: Airbnb | J103: =YEAR(A103)&"-"&TEXT(MONTH(A103),"00") -> 2023-04
A104: 45030 | B104: 45033 | C104: =Table1[[#This Row],[Check-out Date]]-Table1[[#This Row],[Check-in Date]] -> 3 | D104: C301 | E104: Intima | F104: 525 | G104: =Table1[[#This Row],[FULL AMOUNT usd]]*20 -> 10500 | H104: =F104*0.2 -> 105 | I104: Airbnb | J104: =YEAR(A104)&"-"&TEXT(MONTH(A104),"00") -> 2023-04
A105: 45030 | B105: 45033 | C105: =Table1[[#This Row],[Check-out Date]]-Table1[[#This Row],[Check-in Date]] -> 3 | D105: A302 | E105: Intima | F105: 525 | G105: =Table1[[#This Row],[FULL AMOUNT usd]]*20 -> 10500 | H105: =F105*0.2 -> 105 | I105: Direct Reservation | J105: =YEAR(A105)&"-"&TEXT(MONTH(A105),"00") -> 2023-04
A106: 45030 | B106: 45033 | C106: =Table1[[#This Row],[Check-out Date]]-Table1[[#This Row],[Check-in Date]] -> 3 | D106: C301 | F106: 452.71 | G106: =Table1[[#This Row],[FULL AMOUNT usd]]*20 -> 9054.2 | H106: =F106*0.2 -> 90.542 | I106: Airbnb | J106: =YEAR(A106)&"-"&TEXT(MONTH(A106),"00") -> 2023-04
A107: 45033 | B107: 45045 | C107: =Table1[[#This Row],[Check-out Date]]-Table1[[#This Row],[Check-in Date]] -> 12 | D107: B303 | E107: Shelly Morasko | F107: 2618.43 | G107: =Table1[[#This Row],[FULL AMOUNT usd]]*20 -> 52368.6 | H107: =F107*0.2 -> 523.686 | I107: Airbnb | J107: =YEAR(A107)&"-"&TEXT(MONTH(A107),"00") -> 2023-04
A108: 45050 | B108: 45054 | C108: =Table1[[#This Row],[Check-out Date]]-Table1[[#This Row],[Check-in Date]] -> 4 | D108: C301 | F108: 303 | G108: =Table1[[#This Row],[FULL AMOUNT usd]]*20 -> 6060 | H108: =F108*0.2 -> 60.6 | I108: Airbnb | J108: =YEAR(A108)&"-"&TEXT(MONTH(A108),"00") -> 2023-05
A109: 45058 | B109: 45061 | C109: =Table1[[#This Row],[Check-out Date]]-Table1[[#This Row],[Check-in Date]] -> 3 | D109: C301 | E109: Ali Elganzouri | F109: 452.71 | G109: =Table1[[#This Row],[FULL AMOUNT usd]]*20 -> 9054.2 | H109: =F109*0.2 -> 90.542 | I109: Airbnb | J109: =YEAR(A109)&"-"&TEXT(MONTH(A109),"00") -> 2023-05
A110: 45058 | B110: 45061 | C110: =Table1[[#This Row],[Check-out Date]]-Table1[[#This Row],[Check-in Date]] -> 3 | D110: C301 | F110: 335 | G110: =Table1[[#This Row],[FULL AMOUNT usd]]*20 -> 6700 | H110: =F110*0.2 -> 67 | I110: Airbnb | J110: =YEAR(A110)&"-"&TEXT(MONTH(A110),"00") -> 2023-05
A111: 45073 | B111: 45076 | C111: =Table1[[#This Row],[Check-out Date]]-Table1[[#This Row],[Check-in Date]] -> 3 | D111: C301 | E111: Ken Komasuda | F111: 335 | G111: =Table1[[#This Row],[FULL AMOUNT usd]]*20 -> 6700 | H111: =F111*0.2 -> 67 | I111: Direct Reservation | J111: =YEAR(A111)&"-"&TEXT(MONTH(A111),"00") -> 2023-05
A112: 45073 | B112: 45076 | C112: =Table1[[#This Row],[Check-out Date]]-Table1[[#This Row],[Check-in Date]] -> 3 | D112: C301 | F112: 680 | G112: =Table1[[#This Row],[FULL AMOUNT usd]]*20 -> 13600 | H112: =F112*0.2 -> 136 | I112: Airbnb | J112: =YEAR(A112)&"-"&TEXT(MONTH(A112),"00") -> 2023-05
A113: 45080 | B113: 45081 | C113: =Table1[[#This Row],[Check-out Date]]-Table1[[#This Row],[Check-in Date]] -> 1 | D113: A302 | E113: Roberto Quiroz | F113: 111 | G113: =Table1[[#This Row],[FULL AMOUNT usd]]*20 -> 2220 | H113: =F113*0.2 -> 22.2 | I113: Expedia | J113: =YEAR(A113)&"-"&TEXT(MONTH(A113),"00") -> 2023-06
A114: 45097 | B114: 45102 | C114: =Table1[[#This Row],[Check-out Date]]-Table1[[#This Row],[Check-in Date]] -> 5 | D114: C301 | E114: Eric Daninger | F114: 680 | G114: =Table1[[#This Row],[FULL AMOUNT usd]]*20 -> 13600 | H114: =F114*0.2 -> 136 | I114: Direct Reservation | J114: =YEAR(A114)&"-"&TEXT(MONTH(A114),"00") -> 2023-06
A115: 45097 | B115: 45102 | C115: =Table1[[#This Row],[Check-out Date]]-Table1[[#This Row],[Check-in Date]] -> 5 | D115: C301 | F115: 6900 | G115: =Table1[[#This Row],[FULL AMOUNT usd]]*20 -> 138000 | H115: =F115*0.2 -> 1380 | I115: Airbnb | J115: =YEAR(A115)&"-"&TEXT(MONTH(A115),"00") -> 2023-06
A116: 45098 | B116: 45102 | C116: =Table1[[#This Row],[Check-out Date]]-Table1[[#This Row],[Check-in Date]] -> 4 | D116: A302 | E116: Matteo Palacardo | F116: 332.64 | G116: =Table1[[#This Row],[FULL AMOUNT usd]]*20 -> 6652.8 | H116: =F116*0.2 -> 66.528 | I116: Expedia | J116: =YEAR(A116)&"-"&TEXT(MONTH(A116),"00") -> 2023-06
A117: 45099 | B117: 45102 | C117: =Table1[[#This Row],[Check-out Date]]-Table1[[#This Row],[Check-in Date]] -> 3 | D117: A302 | E117: Teresa Suarez | F117: 269 | G117: =Table1[[#This Row],[FULL AMOUNT usd]]*20 -> 5380 | H117: =F117*0.2 -> 53.8 | I117: Direct Reservation | J117: =YEAR(A117)&"-"&TEXT(MONTH(A117),"00") -> 2023-06
A118: 45125 | B118: 45132 | C118: =Table1[[#This Row],[Check-out Date]]-Table1[[#This Row],[Check-in Date]] -> 7 | D118: A302 | E118: Brooke Villanyi | F118: 1027.19 | G118: =Table1[[#This Row],[FULL AMOUNT usd]]*20 -> 20543.8 | H118: =F118*0.2 -> 205.438 | I118: Airbnb | J118: =YEAR(A118)&"-"&TEXT(MONTH(A118),"00") -> 2023-07
A119: 45134 | B119: 45137 | C119: =Table1[[#This Row],[Check-out Date]]-Table1[[#This Row],[Check-in Date]] -> 3 | D119: A302 | E119: Julio Sosa | F119: 265 | G119: =Table1[[#This Row],[FULL AMOUNT usd]]*20 -> 5300 | H119: =F119*0.2 -> 53 | I119: Airbnb | J119: =YEAR(A119)&"-"&TEXT(MONTH(A119),"00") -> 2023-07
A120: 45170 | B120: 45172 | C120: =Table1[[#This Row],[Check-out Date]]-Table1[[#This Row],[Check-in Date]] -> 2 | D120: B303 | E120: Ravin Elango | F120: 6700 | G120: =Table1[[#This Row],[FULL AMOUNT usd]]*20 -> 134000 | H120: =F120*0.2 -> 1340 | I120: Airbnb | J120: =YEAR(A120)&"-"&TEXT(MONTH(A120),"00") -> 2023-09
A121: 45179 | B121: 45183 | C121: =Table1[[#This Row],[Check-out Date]]-Table1[[#This Row],[Check-in Date]] -> 4 | D121: A302 | E121: Gary Mccoy | F121: 238 | G121: =Table1[[#This Row],[FULL AMOUNT usd]]*20 -> 4760 | H121: =F121*0.2 -> 47.6 | I121: Airbnb | J121: =YEAR(A121)&"-"&TEXT(MONTH(A121),"00") -> 2023-09
...

Sheet EXPENSES
A1: DATE | B1: SERVICE | C1: APT | D1: COST $ | E1: TYPE | F1: MONTH
A2: 44576 | B2: Fridge manteinance | C2: B303 | D2: 1658.98 | E2: =IF(OR(C2="A302", C2="B303", C2="C301"), "Direct", "Shared") -> Direct | F2: =YEAR(A2)&"-"&TEXT(MONTH(A2),"00") -> 2022-01
A3: 44576 | B3: Plumber for changing water pump | C3: B303 | D3: 600 | E3: =IF(OR(C3="A302", C3="B303", C3="C301"), "Direct", "Shared") -> Direct | F3: =YEAR(A3)&"-"&TEXT(MONTH(A3),"00") -> 2022-01
A4: 44576 | B4: Roof pool cleaning + chlorine | C4: B303 | D4: 450 | E4: =IF(OR(C4="A302", C4="B303", C4="C301"), "Direct", "Shared") -> Direct | F4: =YEAR(A4)&"-"&TEXT(MONTH(A4),"00") -> 2022-01
A5: 44576 | B5: Lock change entrance door | C5: B303 | D5: 1200 | E5: =IF(OR(C5="A302", C5="B303", C5="C301"), "Direct", "Shared") -> Direct | F5: =YEAR(A5)&"-"&TEXT(MONTH(A5),"00") -> 2022-01
A6: 44576 | B6: Deadbolt instalation | C6: B303 | D6: 500 | E6: =IF(OR(C6="A302", C6="B303", C6="C301"), "Direct", "Shared") -> Direct | F6: =YEAR(A6)&"-"&TEXT(MONTH(A6),"00") -> 2022-01
A7: 44576 | B7: Internet contract | C7: B303 | D7: 5000 | E7: =IF(OR(C7="A302", C7="B303", C7="C301"), "Direct", "Shared") -> Direct | F7: =YEAR(A7)&"-"&TEXT(MONTH(A7),"00") -> 2022-01
A8: 44576 | B8: Table games (Catan, Bycycle cards, Sequence) | C8: Overhead | D8: 1870 | E8: =IF(OR(C8="A302", C8="B303", C8="C301"), "Direct", "Shared") -> Shared | F8: =YEAR(A8)&"-"&TEXT(MONTH(A8),"00") -> 2022-01
A9: 44576 | B9: Dishwasher | C9: B303 | D9: 600 | E9: =IF(OR(C9="A302", C9="B303", C9="C301"), "Direct", "Shared") -> Direct | F9: =YEAR(A9)&"-"&TEXT(MONTH(A9),"00") -> 2022-01
A10: 44579 | B10: Copies documents | C10: Overhead | D10: 18 | E10: =IF(OR(C10="A302", C10="B303", C10="C301"), "Direct", "Shared") -> Shared | F10: =YEAR(A10)&"-"&TEXT(MONTH(A10),"00") -> 2022-01
A11: 44581 | B11: Sliding door fixed (no paint) | C11: B303 | D11: 1400 | E11: =IF(OR(C11="A302", C11="B303", C11="C301"), "Direct", "Shared") -> Direct | F11: =YEAR(A11)&"-"&TEXT(MONTH(A11),"00") -> 2022-01
A12: 44581 | B12: Front door fixed and paint | C12: B303 | D12: 2800 | E12: =IF(OR(C12="A302", C12="B303", C12="C301"), "Direct", "Shared") -> Direct | F12: =YEAR(A12)&"-"&TEXT(MONTH(A12),"00") -> 2022-01
A13: 44581 | B13: Paint 2 sliding doors, door upstairs, windows | C13: B303 | D13: 3800 | E13: =IF(OR(C13="A302", C13="B303", C13="C301"), "Direct", "Shared") -> Direct | F13: =YEAR(A13)&"-"&TEXT(MONTH(A13),"00") -> 2022-01
... A1561: 46160 | B1561: Cleaning 2 bedrooms | C1561: A302 | D1561: 2000 | E1561: =IF(OR(C1561="A302", C1561="B303", C1561="C301"), "Direct", "Shared") -> Direct | F1561: =YEAR(A1561)&"-"&TEXT(MONTH(A1561),"00") -> 2026-05

Sheet Reference_Nights
A1: Month | B1: Apt | C1: Days_in_month | D1: Unavailable_days | E1: Available_nights
A2: 2022-03 | B2: A302 | C2: =DAY(DATE(VALUE(LEFT(A2,4)),VALUE(RIGHT(A2,2))+1,1)-1) -> 31 | D2: 3 | E2: =Reference_Nights[[#This Row],[Days_in_month]]-Reference_Nights[[#This Row],[Unavailable_days]] -> 28
A3: 2022-03 | B3: B303 | C3: =DAY(DATE(VALUE(LEFT(A3,4)),VALUE(RIGHT(A3,2))+1,1)-1) -> 31 | D3: 3 | E3: =Reference_Nights[[#This Row],[Days_in_month]]-Reference_Nights[[#This Row],[Unavailable_days]] -> 28
A4: 2022-03 | B4: C301 | C4: =DAY(DATE(VALUE(LEFT(A4,4)),VALUE(RIGHT(A4,2))+1,1)-1) -> 31 | D4: 3 | E4: =Reference_Nights[[#This Row],[Days_in_month]]-Reference_Nights[[#This Row],[Unavailable_days]] -> 28
A5: 2022-04 | B5: A302 | C5: =DAY(DATE(VALUE(LEFT(A5,4)),VALUE(RIGHT(A5,2))+1,1)-1) -> 30 | D5: 3 | E5: =Reference_Nights[[#This Row],[Days_in_month]]-Reference_Nights[[#This Row],[Unavailable_days]] -> 27
A6: 2022-04 | B6: B303 | C6: =DAY(DATE(VALUE(LEFT(A6,4)),VALUE(RIGHT(A6,2))+1,1)-1) -> 30 | D6: 3 | E6: =Reference_Nights[[#This Row],[Days_in_month]]-Reference_Nights[[#This Row],[Unavailable_days]] -> 27
A7: 2022-04 | B7: C301 | C7: =DAY(DATE(VALUE(LEFT(A7,4)),VALUE(RIGHT(A7,2))+1,1)-1) -> 30 | D7: 3 | E7: =Reference_Nights[[#This Row],[Days_in_month]]-Reference_Nights[[#This Row],[Unavailable_days]] -> 27
A8: 2022-05 | B8: A302 | C8: =DAY(DATE(VALUE(LEFT(A8,4)),VALUE(RIGHT(A8,2))+1,1)-1) -> 31 | D8: 3 | E8: =Reference_Nights[[#This Row],[Days_in_month]]-Reference_Nights[[#This Row],[Unavailable_days]] -> 28
A9: 2022-05 | B9: B303 | C9: =DAY(DATE(VALUE(LEFT(A9,4)),VALUE(RIGHT(A9,2))+1,1)-1) -> 31 | D9: 3 | E9: =Reference_Nights[[#This Row],[Days_in_month]]-Reference_Nights[[#This Row],[Unavailable_days]] -> 28
A10: 2022-05 | B10: C301 | C10: =DAY(DATE(VALUE(LEFT(A10,4)),VALUE(RIGHT(A10,2))+1,1)-1) -> 31 | D10: 3 | E10: =Reference_Nights[[#This Row],[Days_in_month]]-Reference_Nights[[#This Row],[Unavailable_days]] -> 28
A11: 2022-06 | B11: A302 | C11: =DAY(DATE(VALUE(LEFT(A11,4)),VALUE(RIGHT(A11,2))+1,1)-1) -> 30 | D11: 3 | E11: =Reference_Nights[[#This Row],[Days_in_month]]-Reference_Nights[[#This Row],[Unavailable_days]] -> 27
A12: 2022-06 | B12: B303 | C12: =DAY(DATE(VALUE(LEFT(A12,4)),VALUE(RIGHT(A12,2))+1,1)-1) -> 30 | D12: 3 | E12: =Reference_Nights[[#This Row],[Days_in_month]]-Reference_Nights[[#This Row],[Unavailable_days]] -> 27
A13: 2022-06 | B13: C301 | C13: =DAY(DATE(VALUE(LEFT(A13,4)),VALUE(RIGHT(A13,2))+1,1)-1) -> 30 | D13: 3 | E13: =Reference_Nights[[#This Row],[Days_in_month]]-Reference_Nights[[#This Row],[Unavailable_days]] -> 27
... A154: 2026-05 | B154: C301 | C154: =DAY(DATE(VALUE(LEFT(A154,4)),VALUE(RIGHT(A154,2))+1,1)-1) -> 31 | D154: 3 | E154: =Reference_Nights[[#This Row],[Days_in_month]]-Reference_Nights[[#This Row],[Unavailable_days]] -> 28

Sheet Data_Consolidado
A1: Month | B1: Apt | C1: Income | D1: Booked_Nights | E1: Exp_Direct | F1: Pct_Income | G1: Shared_Total | H1: Shared_Assigned | I1: Total_Exp | J1: Profit_or_Loss | K1: Margin% | L1: Available _Nights | M1: Occupancy_Rate | N1: Avg_Daily_Rate | O1: Rev_per_Av_Night | P1: Expense_Ratio%
A2: 2022-01 | B2: A302 | C2: =SUMIFS(Table1[FULL AMOUNT mxn pesos], Table1[Month], A2, Table1[APARTMENT], B2) -> 0 | D2: =SUMIFS(INCOME!C:C, INCOME!D:D, Table2[[#This Row],[Apt]], INCOME!J:J, Table2[[#This Row],[Month]]) -> 0 | E2: =SUMIFS(EXPENSES!$D:$D, EXPENSES!$C:$C, B2, EXPENSES!$F:$F, A2, EXPENSES!$E:$E, "Direct") -> 3464.76 | F2: =IF(C2=0,0,C2/SUMIF(A:A,A2,C:C)) -> 0 | G2: =SUMIFS(EXPENSES!D:D, EXPENSES!F:F, Data_Consolidado!A2, EXPENSES!E:E, "Shared") -> 5188 | H2: =Table2[[#This Row],[Shared_Total]]/2 -> 2594 | I2: =E2+H2 -> 6058.76 | J2: =C2-I2 -> -6058.76 | K2: =IF(C2=0, "-", (J2/C2)) -> - | L2: =SUMIFS(Reference_Nights[[#All],[Available_nights]], Reference_Nights[[#All],[Month]], Table2[[#This Row],[Month]], Reference_Nights[[#All],[Apt]], Table2[[#This Row],[Apt]]) -> 0 | M2: =IF(Table2[[#This Row],[Available _Nights]]=0, 0, Table2[[#This Row],[Booked_Nights]]/Table2[[#This Row],[Available _Nights]]) -> 0 | N2: =IF(Table2[[#This Row],[Booked_Nights]]=0, 0, Table2[[#This Row],[Income]]/Table2[[#This Row],[Booked_Nights]]) -> 0 | O2: =IF(L2=0,0, Table2[[#This Row],[Income]]/Table2[[#This Row],[Available _Nights]]) -> 0 | P2: =IF(Table2[[#This Row],[Income]]=0,0,Table2[[#This Row],[Total_Exp]]/Table2[[#This Row],[Income]]) -> 0
A3: 2022-01 | B3: B303 | C3: =SUMIFS(Table1[FULL AMOUNT mxn pesos], Table1[Month], A3, Table1[APARTMENT], B3) -> 0 | D3: =SUMIFS(INCOME!C:C, INCOME!D:D, Table2[[#This Row],[Apt]], INCOME!J:J, Table2[[#This Row],[Month]]) -> 0 | E3: =SUMIFS(EXPENSES!$D:$D, EXPENSES!$C:$C, B3, EXPENSES!$F:$F, A3, EXPENSES!$E:$E, "Direct") -> 39110.72 | F3: =IF(C3=0,0,C3/SUMIF(A:A,A3,C:C)) -> 0 | G3: =SUMIFS(EXPENSES!D:D, EXPENSES!F:F, Data_Consolidado!A3, EXPENSES!E:E, "Shared") -> 5188 | H3: =Table2[[#This Row],[Shared_Total]]/2 -> 2594 | I3: =E3+H3 -> 41704.72 | J3: =C3-I3 -> -41704.72 | K3: =IF(C3=0, "-", (J3/C3)) -> - | L3: =SUMIFS(Reference_Nights[[#All],[Available_nights]], Reference_Nights[[#All],[Month]], Table2[[#This Row],[Month]], Reference_Nights[[#All],[Apt]], Table2[[#This Row],[Apt]]) -> 0 | M3: =IF(Table2[[#This Row],[Available _Nights]]=0, 0, Table2[[#This Row],[Booked_Nights]]/Table2[[#This Row],[Available _Nights]]) -> 0 | N3: =IF(Table2[[#This Row],[Booked_Nights]]=0, 0, Table2[[#This Row],[Income]]/Table2[[#This Row],[Booked_Nights]]) -> 0 | O3: =IF(L3=0,0, Table2[[#This Row],[Income]]/Table2[[#This Row],[Available _Nights]]) -> 0 | P3: =IF(Table2[[#This Row],[Income]]=0,0,Table2[[#This Row],[Total_Exp]]/Table2[[#This Row],[Income]]) -> 0
A4: 2022-02 | B4: A302 | C4: =SUMIFS(Table1[FULL AMOUNT mxn pesos], Table1[Month], A4, Table1[APARTMENT], B4) -> 0 | D4: =SUMIFS(INCOME!C:C, INCOME!D:D, Table2[[#This Row],[Apt]], INCOME!J:J, Table2[[#This Row],[Month]]) -> 0 | E4: =SUMIFS(EXPENSES!$D:$D, EXPENSES!$C:$C, B4, EXPENSES!$F:$F, A4, EXPENSES!$E:$E, "Direct") -> 9560 | F4: =IF(C4=0,0,C4/SUMIF(A:A,A4,C:C)) -> 0 | G4: =SUMIFS(EXPENSES!D:D, EXPENSES!F:F, Data_Consolidado!A4, EXPENSES!E:E, "Shared") -> 1240 | H4: =Table2[[#This Row],[Shared_Total]]/2 -> 620 | I4: =E4+H4 -> 10180 | J4: =C4-I4 -> -10180 | K4: =IF(C4=0, "-", (J4/C4)) -> - | L4: =SUMIFS(Reference_Nights[[#All],[Available_nights]], Reference_Nights[[#All],[Month]], Table2[[#This Row],[Month]], Reference_Nights[[#All],[Apt]], Table2[[#This Row],[Apt]]) -> 0 | M4: =IF(Table2[[#This Row],[Available _Nights]]=0, 0, Table2[[#This Row],[Booked_Nights]]/Table2[[#This Row],[Available _Nights]]) -> 0 | N4: =IF(Table2[[#This Row],[Booked_Nights]]=0, 0, Table2[[#This Row],[Income]]/Table2[[#This Row],[Booked_Nights]]) -> 0 | O4: =IF(L4=0,0, Table2[[#This Row],[Income]]/Table2[[#This Row],[Available _Nights]]) -> 0 | P4: =IF(Table2[[#This Row],[Income]]=0,0,Table2[[#This Row],[Total_Exp]]/Table2[[#This Row],[Income]]) -> 0
A5: 2022-02 | B5: B303 | C5: =SUMIFS(Table1[FULL AMOUNT mxn pesos], Table1[Month], A5, Table1[APARTMENT], B5) -> 0 | D5: =SUMIFS(INCOME!C:C, INCOME!D:D, Table2[[#This Row],[Apt]], INCOME!J:J, Table2[[#This Row],[Month]]) -> 0 | E5: =SUMIFS(EXPENSES!$D:$D, EXPENSES!$C:$C, B5, EXPENSES!$F:$F, A5, EXPENSES!$E:$E, "Direct") -> 26307 | F5: =IF(C5=0,0,C5/SUMIF(A:A,A5,C:C)) -> 0 | G5: =SUMIFS(EXPENSES!D:D, EXPENSES!F:F, Data_Consolidado!A5, EXPENSES!E:E, "Shared") -> 1240 | H5: =Table2[[#This Row],[Shared_Total]]/2 -> 620 | I5: =E5+H5 -> 26927 | J5: =C5-I5 -> -26927 | K5: =IF(C5=0, "-", (J5/C5)) -> - | L5: =SUMIFS(Reference_Nights[[#All],[Available_nights]], Reference_Nights[[#All],[Month]], Table2[[#This Row],[Month]], Reference_Nights[[#All],[Apt]], Table2[[#This Row],[Apt]]) -> 0 | M5: =IF(Table2[[#This Row],[Available _Nights]]=0, 0, Table2[[#This Row],[Booked_Nights]]/Table2[[#This Row],[Available _Nights]]) -> 0 | N5: =IF(Table2[[#This Row],[Booked_Nights]]=0, 0, Table2[[#This Row],[Income]]/Table2[[#This Row],[Booked_Nights]]) -> 0 | O5: =IF(L5=0,0, Table2[[#This Row],[Income]]/Table2[[#This Row],[Available _Nights]]) -> 0 | P5: =IF(Table2[[#This Row],[Income]]=0,0,Table2[[#This Row],[Total_Exp]]/Table2[[#This Row],[Income]]) -> 0
A6: 2022-03 | B6: A302 | C6: =SUMIFS(Table1[FULL AMOUNT mxn pesos], Table1[Month], A6, Table1[APARTMENT], B6) -> 33655.8 | D6: =SUMIFS(INCOME!C:C, INCOME!D:D, Table2[[#This Row],[Apt]], INCOME!J:J, Table2[[#This Row],[Month]]) -> 23 | E6: =SUMIFS(EXPENSES!$D:$D, EXPENSES!$C:$C, B6, EXPENSES!$F:$F, A6, EXPENSES!$E:$E, "Direct") -> 5533 | F6: =IF(C6=0,0,C6/SUMIF(A:A,A6,C:C)) -> 0.50731065 | G6: =SUMIFS(EXPENSES!D:D, EXPENSES!F:F, Data_Consolidado!A6, EXPENSES!E:E, "Shared") -> 7565.5 | H6: =G6*F6 -> 3838.0587 | I6: =E6+H6 -> 9371.0587 | J6: =C6-I6 -> 24284.741 | K6: =IF(C6=0, "-", (J6/C6)) -> 0.72156185 | L6: =SUMIFS(Reference_Nights[[#All],[Available_nights]], Reference_Nights[[#All],[Month]], Table2[[#This Row],[Month]], Reference_Nights[[#All],[Apt]], Table2[[#This Row],[Apt]]) -> 28 | M6: =IF(Table2[[#This Row],[Available _Nights]]=0, 0, Table2[[#This Row],[Booked_Nights]]/Table2[[#This Row],[Available _Nights]]) -> 0.82142857 | N6: =IF(Table2[[#This Row],[Booked_Nights]]=0, 0, Table2[[#This Row],[Income]]/Table2[[#This Row],[Booked_Nights]]) -> 1463.2957 | O6: =IF(L6=0,0, Table2[[#This Row],[Income]]/Table2[[#This Row],[Available _Nights]]) -> 1201.9929 | P6: =IF(Table2[[#This Row],[Income]]=0,0,Table2[[#This Row],[Total_Exp]]/Table2[[#This Row],[Income]]) -> 0.27843815
A7: 2022-03 | B7: B303 | C7: =SUMIFS(Table1[FULL AMOUNT mxn pesos], Table1[Month], A7, Table1[APARTMENT], B7) -> 32685.8 | D7: =SUMIFS(INCOME!C:C, INCOME!D:D, Table2[[#This Row],[Apt]], INCOME!J:J, Table2[[#This Row],[Month]]) -> 21 | E7: =SUMIFS(EXPENSES!$D:$D, EXPENSES!$C:$C, B7, EXPENSES!$F:$F, A7, EXPENSES!$E:$E, "Direct") -> 16096.75 | F7: =IF(C7=0,0,C7/SUMIF(A:A,A7,C:C)) -> 0.49268935 | G7: =SUMIFS(EXPENSES!D:D, EXPENSES!F:F, Data_Consolidado!A7, EXPENSES!E:E, "Shared") -> 7565.5 | H7: =G7*F7 -> 3727.4413 | I7: =E7+H7 -> 19824.191 | J7: =C7-I7 -> 12861.609 | K7: =IF(C7=0, "-", (J7/C7)) -> 0.39349224 | L7: =SUMIFS(Reference_Nights[[#All],[Available_nights]], Reference_Nights[[#All],[Month]], Table2[[#This Row],[Month]], Reference_Nights[[#All],[Apt]], Table2[[#This Row],[Apt]]) -> 28 | M7: =IF(Table2[[#This Row],[Available _Nights]]=0, 0, Table2[[#This Row],[Booked_Nights]]/Table2[[#This Row],[Available _Nights]]) -> 0.75 | N7: =IF(Table2[[#This Row],[Booked_Nights]]=0, 0, Table2[[#This Row],[Income]]/Table2[[#This Row],[Booked_Nights]]) -> 1556.4667 | O7: =IF(L7=0,0, Table2[[#This Row],[Income]]/Table2[[#This Row],[Available _Nights]]) -> 1167.35 | P7: =IF(Table2[[#This Row],[Income]]=0,0,Table2[[#This Row],[Total_Exp]]/Table2[[#This Row],[Income]]) -> 0.60650776
A8: 2022-04 | B8: A302 | C8: =SUMIFS(Table1[FULL AMOUNT mxn pesos], Table1[Month], A8, Table1[APARTMENT], B8) -> 68562.6 | D8: =SUMIFS(INCOME!C:C, INCOME!D:D, Table2[[#This Row],[Apt]], INCOME!J:J, Table2[[#This Row],[Month]]) -> 26 | E8: =SUMIFS(EXPENSES!$D:$D, EXPENSES!$C:$C, B8, EXPENSES!$F:$F, A8, EXPENSES!$E:$E, "Direct") -> 11030 | F8: =IF(C8=0,0,C8/SUMIF(A:A,A8,C:C)) -> 0.58247246 | G8: =SUMIFS(EXPENSES!D:D, EXPENSES!F:F, Data_Consolidado!A8, EXPENSES!E:E, "Shared") -> 10324 | H8: =G8*F8 -> 6013.4457 | I8: =E8+H8 -> 17043.446 | J8: =C8-I8 -> 51519.154 | K8: =IF(C8=0, "-", (J8/C8)) -> 0.75141775 | L8: =SUMIFS(Reference_Nights[[#All],[Available_nights]], Reference_Nights[[#All],[Month]], Table2[[#This Row],[Month]], Reference_Nights[[#All],[Apt]], Table2[[#This Row],[Apt]]) -> 27 | M8: =IF(Table2[[#This Row],[Available _Nights]]=0, 0, Table2[[#This Row],[Booked_Nights]]/Table2[[#This Row],[Available _Nights]]) -> 0.96296296 | N8: =IF(Table2[[#This Row],[Booked_Nights]]=0, 0, Table2[[#This Row],[Income]]/Table2[[#This Row],[Booked_Nights]]) -> 2637.0231 | O8: =IF(L8=0,0, Table2[[#This Row],[Income]]/Table2[[#This Row],[Available _Nights]]) -> 2539.3556 | P8: =IF(Table2[[#This Row],[Income]]=0,0,Table2[[#This Row],[Total_Exp]]/Table2[[#This Row],[Income]]) -> 0.24858225
A9: 2022-04 | B9: B303 | C9: =SUMIFS(Table1[FULL AMOUNT mxn pesos], Table1[Month], A9, Table1[APARTMENT], B9) -> 49147 | D9: =SUMIFS(INCOME!C:C, INCOME!D:D, Table2[[#This Row],[Apt]], INCOME!J:J, Table2[[#This Row],[Month]]) -> 21 | E9: =SUMIFS(EXPENSES!$D:$D, EXPENSES!$C:$C, B9, EXPENSES!$F:$F, A9, EXPENSES!$E:$E, "Direct") -> 6170 | F9: =IF(C9=0,0,C9/SUMIF(A:A,A9,C:C)) -> 0.41752754 | G9: =SUMIFS(EXPENSES!D:D, EXPENSES!F:F, Data_Consolidado!A9, EXPENSES!E:E, "Shared") -> 10324 | H9: =G9*F9 -> 4310.5543 | I9: =E9+H9 -> 10480.554 | J9: =C9-I9 -> 38666.446 | K9: =IF(C9=0, "-", (J9/C9)) -> 0.78675088 | L9: =SUMIFS(Reference_Nights[[#All],[Available_nights]], Reference_Nights[[#All],[Month]], Table2[[#This Row],[Month]], Reference_Nights[[#All],[Apt]], Table2[[#This Row],[Apt]]) -> 27 | M9: =IF(Table2[[#This Row],[Available _Nights]]=0, 0, Table2[[#This Row],[Booked_Nights]]/Table2[[#This Row],[Available _Nights]]) -> 0.77777778 | N9: =IF(Table2[[#This Row],[Booked_Nights]]=0, 0, Table2[[#This Row],[Income]]/Table2[[#This Row],[Booked_Nights]]) -> 2340.3333 | O9: =IF(L9=0,0, Table2[[#This Row],[Income]]/Table2[[#This Row],[Available _Nights]]) -> 1820.2593 | P9: =IF(Table2[[#This Row],[Income]]=0,0,Table2[[#This Row],[Total_Exp]]/Table2[[#This Row],[Income]]) -> 0.21324912
A10: 2022-05 | B10: A302 | C10: =SUMIFS(Table1[FULL AMOUNT mxn pesos], Table1[Month], A10, Table1[APARTMENT], B10) -> 71984.2 | D10: =SUMIFS(INCOME!C:C, INCOME!D:D, Table2[[#This Row],[Apt]], INCOME!J:J, Table2[[#This Row],[Month]]) -> 35 | E10: =SUMIFS(EXPENSES!$D:$D, EXPENSES!$C:$C, B10, EXPENSES!$F:$F, A10, EXPENSES!$E:$E, "Direct") -> 6916 | F10: =IF(C10=0,0,C10/SUMIF(A:A,A10,C:C)) -> 0.55374677 | G10: =SUMIFS(EXPENSES!D:D, EXPENSES!F:F, Data_Consolidado!A10, EXPENSES!E:E, "Shared") -> 8041 | H10: =G10*F10 -> 4452.6777 | I10: =E10+H10 -> 11368.678 | J10: =C10-I10 -> 60615.522 | K10: =IF(C10=0, "-", (J10/C10)) -> 0.84206704 | L10: =SUMIFS(Reference_Nights[[#All],[Available_nights]], Reference_Nights[[#All],[Month]], Table2[[#This Row],[Month]], Reference_Nights[[#All],[Apt]], Table2[[#This Row],[Apt]]) -> 28 | M10: =IF(Table2[[#This Row],[Available _Nights]]=0, 0, Table2[[#This Row],[Booked_Nights]]/Table2[[#This Row],[Available _Nights]]) -> 1.25 | N10: =IF(Table2[[#This Row],[Booked_Nights]]=0, 0, Table2[[#This Row],[Income]]/Table2[[#This Row],[Booked_Nights]]) -> 2056.6914 | O10: =IF(L10=0,0, Table2[[#This Row],[Income]]/Table2[[#This Row],[Available _Nights]]) -> 2570.8643 | P10: =IF(Table2[[#This Row],[Income]]=0,0,Table2[[#This Row],[Total_Exp]]/Table2[[#This Row],[Income]]) -> 0.15793296
A11: 2022-05 | B11: B303 | C11: =SUMIFS(Table1[FULL AMOUNT mxn pesos], Table1[Month], A11, Table1[APARTMENT], B11) -> 58010.6 | D11: =SUMIFS(INCOME!C:C, INCOME!D:D, Table2[[#This Row],[Apt]], INCOME!J:J, Table2[[#This Row],[Month]]) -> 28 | E11: =SUMIFS(EXPENSES!$D:$D, EXPENSES!$C:$C, B11, EXPENSES!$F:$F, A11, EXPENSES!$E:$E, "Direct") -> 6591 | F11: =IF(C11=0,0,C11/SUMIF(A:A,A11,C:C)) -> 0.44625323 | G11: =SUMIFS(EXPENSES!D:D, EXPENSES!F:F, Data_Consolidado!A11, EXPENSES!E:E, "Shared") -> 8041 | H11: =G11*F11 -> 3588.3223 | I11: =E11+H11 -> 10179.322 | J11: =C11-I11 -> 47831.278 | K11: =IF(C11=0, "-", (J11/C11)) -> 0.82452651 | L11: =SUMIFS(Reference_Nights[[#All],[Available_nights]], Reference_Nights[[#All],[Month]], Table2[[#This Row],[Month]], Reference_Nights[[#All],[Apt]], Table2[[#This Row],[Apt]]) -> 28 | M11: =IF(Table2[[#This Row],[Available _Nights]]=0, 0, Table2[[#This Row],[Booked_Nights]]/Table2[[#This Row],[Available _Nights]]) -> 1 | N11: =IF(Table2[[#This Row],[Booked_Nights]]=0, 0, Table2[[#This Row],[Income]]/Table2[[#This Row],[Booked_Nights]]) -> 2071.8071 | O11: =IF(L11=0,0, Table2[[#This Row],[Income]]/Table2[[#This Row],[Available _Nights]]) -> 2071.8071 | P11: =IF(Table2[[#This Row],[Income]]=0,0,Table2[[#This Row],[Total_Exp]]/Table2[[#This Row],[Income]]) -> 0.17547349
A12: 2022-06 | B12: A302 | C12: =SUMIFS(Table1[FULL AMOUNT mxn pesos], Table1[Month], A12, Table1[APARTMENT], B12) -> 9130.4 | D12: =SUMIFS(INCOME!C:C, INCOME!D:D, Table2[[#This Row],[Apt]], INCOME!J:J, Table2[[#This Row],[Month]]) -> 6 | E12: =SUMIFS(EXPENSES!$D:$D, EXPENSES!$C:$C, B12, EXPENSES!$F:$F, A12, EXPENSES!$E:$E, "Direct") -> 4015 | F12: =IF(C12=0,0,C12/SUMIF(A:A,A12,C:C)) -> 0.2534434 | G12: =SUMIFS(EXPENSES!D:D, EXPENSES!F:F, Data_Consolidado!A12, EXPENSES!E:E, "Shared") -> 7602 | H12: =G12*F12 -> 1926.6768 | I12: =E12+H12 -> 5941.6768 | J12: =C12-I12 -> 3188.7232 | K12: =IF(C12=0, "-", (J12/C12)) -> 0.34924245 | L12: =SUMIFS(Reference_Nights[[#All],[Available_nights]], Reference_Nights[[#All],[Month]], Table2[[#This Row],[Month]], Reference_Nights[[#All],[Apt]], Table2[[#This Row],[Apt]]) -> 27 | M12: =IF(Table2[[#This Row],[Available _Nights]]=0, 0, Table2[[#This Row],[Booked_Nights]]/Table2[[#This Row],[Available _Nights]]) -> 0.22222222 | N12: =IF(Table2[[#This Row],[Booked_Nights]]=0, 0, Table2[[#This Row],[Income]]/Table2[[#This Row],[Booked_Nights]]) -> 1521.7333 | O12: =IF(L12=0,0, Table2[[#This Row],[Income]]/Table2[[#This Row],[Available _Nights]]) -> 338.16296 | P12: =IF(Table2[[#This Row],[Income]]=0,0,Table2[[#This Row],[Total_Exp]]/Table2[[#This Row],[Income]]) -> 0.65075755
A13: 2022-06 | B13: B303 | C13: =SUMIFS(Table1[FULL AMOUNT mxn pesos], Table1[Month], A13, Table1[APARTMENT], B13) -> 26895 | D13: =SUMIFS(INCOME!C:C, INCOME!D:D, Table2[[#This Row],[Apt]], INCOME!J:J, Table2[[#This Row],[Month]]) -> 15 | E13: =SUMIFS(EXPENSES!$D:$D, EXPENSES!$C:$C, B13, EXPENSES!$F:$F, A13, EXPENSES!$E:$E, "Direct") -> 8211 | F13: =IF(C13=0,0,C13/SUMIF(A:A,A13,C:C)) -> 0.7465566 | G13: =SUMIFS(EXPENSES!D:D, EXPENSES!F:F, Data_Consolidado!A13, EXPENSES!E:E, "Shared") -> 7602 | H13: =G13*F13 -> 5675.3232 | I13: =E13+H13 -> 13886.323 | J13: =C13-I13 -> 13008.677 | K13: =IF(C13=0, "-", (J13/C13)) -> 0.48368384 | L13: =SUMIFS(Reference_Nights[[#All],[Available_nights]], Reference_Nights[[#All],[Month]], Table2[[#This Row],[Month]], Reference_Nights[[#All],[Apt]], Table2[[#This Row],[Apt]]) -> 27 | M13: =IF(Table2[[#This Row],[Available _Nights]]=0, 0, Table2[[#This Row],[Booked_Nights]]/Table2[[#This Row],[Available _Nights]]) -> 0.55555556 | N13: =IF(Table2[[#This Row],[Booked_Nights]]=0, 0, Table2[[#This Row],[Income]]/Table2[[#This Row],[Booked_Nights]]) -> 1793 | O13: =IF(L13=0,0, Table2[[#This Row],[Income]]/Table2[[#This Row],[Available _Nights]]) -> 996.11111 | P13: =IF(Table2[[#This Row],[Income]]=0,0,Table2[[#This Row],[Total_Exp]]/Table2[[#This Row],[Income]]) -> 0.51631616
A14: 2022-06 | B14: C301 | C14: =SUMIFS(Table1[FULL AMOUNT mxn pesos], Table1[Month], A14, Table1[APARTMENT], B14) -> 0 | D14: =SUMIFS(INCOME!C:C, INCOME!D:D, Table2[[#This Row],[Apt]], INCOME!J:J, Table2[[#This Row],[Month]]) -> 0 | E14: =SUMIFS(EXPENSES!$D:$D, EXPENSES!$C:$C, B14, EXPENSES!$F:$F, A14, EXPENSES!$E:$E, "Direct") -> 2600 | F14: =IF(C14=0,0,C14/SUMIF(A:A,A14,C:C)) -> 0 | G14: =SUMIFS(EXPENSES!D:D, EXPENSES!F:F, Data_Consolidado!A14, EXPENSES!E:E, "Shared") -> 7602 | H14: =G14*F14 -> 0 | I14: =E14+H14 -> 2600 | J14: =C14-I14 -> -2600 | K14: =IF(C14=0, "-", (J14/C14)) -> - | L14: =SUMIFS(Reference_Nights[[#All],[Available_nights]], Reference_Nights[[#All],[Month]], Table2[[#This Row],[Month]], Reference_Nights[[#All],[Apt]], Table2[[#This Row],[Apt]]) -> 27 | M14: =IF(Table2[[#This Row],[Available _Nights]]=0, 0, Table2[[#This Row],[Booked_Nights]]/Table2[[#This Row],[Available _Nights]]) -> 0 | N14: =IF(Table2[[#This Row],[Booked_Nights]]=0, 0, Table2[[#This Row],[Income]]/Table2[[#This Row],[Booked_Nights]]) -> 0 | O14: =IF(L14=0,0, Table2[[#This Row],[Income]]/Table2[[#This Row],[Available _Nights]]) -> 0 | P14: =IF(Table2[[#This Row],[Income]]=0,0,Table2[[#This Row],[Total_Exp]]/Table2[[#This Row],[Income]]) -> 0
A15: 2022-07 | B15: A302 | C15: =SUMIFS(Table1[FULL AMOUNT mxn pesos], Table1[Month], A15, Table1[APARTMENT], B15) -> 43007.8 | D15: =SUMIFS(INCOME!C:C, INCOME!D:D, Table2[[#This Row],[Apt]], INCOME!J:J, Table2[[#This Row],[Month]]) -> 13 | E15: =SUMIFS(EXPENSES!$D:$D, EXPENSES!$C:$C, B15, EXPENSES!$F:$F, A15, EXPENSES!$E:$E, "Direct") -> 13166 | F15: =IF(C15=0,0,C15/SUMIF(A:A,A15,C:C)) -> 0.48660055 | G15: =SUMIFS(EXPENSES!D:D, EXPENSES!F:F, Data_Consolidado!A15, EXPENSES!E:E, "Shared") -> 10489 | H15: =G15*F15 -> 5103.9531 | I15: =E15+H15 -> 18269.953 | J15: =C15-I15 -> 24737.847 | K15: =IF(C15=0, "-", (J15/C15)) -> 0.57519443 | L15: =SUMIFS(Reference_Nights[[#All],[Available_nights]], Reference_Nights[[#All],[Month]], Table2[[#This Row],[Month]], Reference_Nights[[#All],[Apt]], Table2[[#This Row],[Apt]]) -> 28 | M15: =IF(Table2[[#This Row],[Available _Nights]]=0, 0, Table2[[#This Row],[Booked_Nights]]/Table2[[#This Row],[Available _Nights]]) -> 0.46428571 | N15: =IF(Table2[[#This Row],[Booked_Nights]]=0, 0, Table2[[#This Row],[Income]]/Table2[[#This Row],[Booked_Nights]]) -> 3308.2923 | O15: =IF(L15=0,0, Table2[[#This Row],[Income]]/Table2[[#This Row],[Available _Nights]]) -> 1535.9929 | P15: =IF(Table2[[#This Row],[Income]]=0,0,Table2[[#This Row],[Total_Exp]]/Table2[[#This Row],[Income]]) -> 0.42480557
A16: 2022-07 | B16: B303 | C16: =SUMIFS(Table1[FULL AMOUNT mxn pesos], Table1[Month], A16, Table1[APARTMENT], B16) -> 45376.4 | D16: =SUMIFS(INCOME!C:C, INCOME!D:D, Table2[[#This Row],[Apt]], INCOME!J:J, Table2[[#This Row],[Month]]) -> 22 | E16: =SUMIFS(EXPENSES!$D:$D, EXPENSES!$C:$C, B16, EXPENSES!$F:$F, A16, EXPENSES!$E:$E, "Direct") -> 14801 | F16: =IF(C16=0,0,C16/SUMIF(A:A,A16,C:C)) -> 0.51339945 | G16: =SUMIFS(EXPENSES!D:D, EXPENSES!F:F, Data_Consolidado!A16, EXPENSES!E:E, "Shared") -> 10489 | H16: =G16*F16 -> 5385.0469 | I16: =E16+H16 -> 20186.047 | J16: =C16-I16 -> 25190.353 | K16: =IF(C16=0, "-", (J16/C16)) -> 0.55514217 | L16: =SUMIFS(Reference_Nights[[#All],[Available_nights]], Reference_Nights[[#All],[Month]], Table2[[#This Row],[Month]], Reference_Nights[[#All],[Apt]], Table2[[#This Row],[Apt]]) -> 28 | M16: =IF(Table2[[#This Row],[Available _Nights]]=0, 0, Table2[[#This Row],[Booked_Nights]]/Table2[[#This Row],[Available _Nights]]) -> 0.78571429 | N16: =IF(Table2[[#This Row],[Booked_Nights]]=0, 0, Table2[[#This Row],[Income]]/Table2[[#This Row],[Booked_Nights]]) -> 2062.5636 | O16: =IF(L16=0,0, Table2[[#This Row],[Income]]/Table2[[#This Row],[Available _Nights]]) -> 1620.5857 | P16: =IF(Table2[[#This Row],[Income]]=0,0,Table2[[#This Row],[Total_Exp]]/Table2[[#This Row],[Income]]) -> 0.44485783
A17: 2022-07 | B17: C301 | C17: =SUMIFS(Table1[FULL AMOUNT mxn pesos], Table1[Month], A17, Table1[APARTMENT], B17) -> 0 | D17: =SUMIFS(INCOME!C:C, INCOME!D:D, Table2[[#This Row],[Apt]], INCOME!J:J, Table2[[#This Row],[Month]]) -> 0 | E17: =SUMIFS(EXPENSES!$D:$D, EXPENSES!$C:$C, B17, EXPENSES!$F:$F, A17, EXPENSES!$E:$E, "Direct") -> 10533 | F17: =IF(C17=0,0,C17/SUMIF(A:A,A17,C:C)) -> 0 | G17: =SUMIFS(EXPENSES!D:D, EXPENSES!F:F, Data_Consolidado!A17, EXPENSES!E:E, "Shared") -> 10489 | H17: =G17*F17 -> 0 | I17: =E17+H17 -> 10533 | J17: =C17-I17 -> -10533 | K17: =IF(C17=0, "-", (J17/C17)) -> - | L17: =SUMIFS(Reference_Nights[[#All],[Available_nights]], Reference_Nights[[#All],[Month]], Table2[[#This Row],[Month]], Reference_Nights[[#All],[Apt]], Table2[[#This Row],[Apt]]) -> 28 | M17: =IF(Table2[[#This Row],[Available _Nights]]=0, 0, Table2[[#This Row],[Booked_Nights]]/Table2[[#This Row],[Available _Nights]]) -> 0 | N17: =IF(Table2[[#This Row],[Booked_Nights]]=0, 0, Table2[[#This Row],[Income]]/Table2[[#This Row],[Booked_Nights]]) -> 0 | O17: =IF(L17=0,0, Table2[[#This Row],[Income]]/Table2[[#This Row],[Available _Nights]]) -> 0 | P17: =IF(Table2[[#This Row],[Income]]=0,0,Table2[[#This Row],[Total_Exp]]/Table2[[#This Row],[Income]]) -> 0
... A20: 2022-08 | B20: C301 | C20: =SUMIFS(Table1[FULL AMOUNT mxn pesos], Table1[Month], A20, Table1[APARTMENT], B20) -> 19489.2 | D20: =SUMIFS(INCOME!C:C, INCOME!D:D, Table2[[#This Row],[Apt]], INCOME!J:J, Table2[[#This Row],[Month]]) -> 17 | E20: =SUMIFS(EXPENSES!$D:$D, EXPENSES!$C:$C, B20, EXPENSES!$F:$F, A20, EXPENSES!$E:$E, "Direct") -> 49302 | F20: =IF(C20=0,0,C20/SUMIF(A:A,A20,C:C)) -> 0.33803843 | G20: =SUMIFS(EXPENSES!D:D, EXPENSES!F:F, Data_Consolidado!A20, EXPENSES!E:E, "Shared") -> 14507 | H20: =G20*F20 -> 4903.9235 | I20: =E20+H20 -> 54205.923 | J20: =C20-I20 -> -34716.723 | K20: =IF(C20=0, "-", (J20/C20)) -> -1.7813314 | L20: =SUMIFS(Reference_Nights[[#All],[Available_nights]], Reference_Nights[[#All],[Month]], Table2[[#This Row],[Month]], Reference_Nights[[#All],[Apt]], Table2[[#This Row],[Apt]]) -> 28 | M20: =IF(Table2[[#This Row],[Available _Nights]]=0, 0, Table2[[#This Row],[Booked_Nights]]/Table2[[#This Row],[Available _Nights]]) -> 0.60714286 | N20: =IF(Table2[[#This Row],[Booked_Nights]]=0, 0, Table2[[#This Row],[Income]]/Table2[[#This Row],[Booked_Nights]]) -> 1146.4235 | O20: =IF(L20=0,0, Table2[[#This Row],[Income]]/Table2[[#This Row],[Available _Nights]]) -> 696.04286 | P20: =IF(Table2[[#This Row],[Income]]=0,0,Table2[[#This Row],[Total_Exp]]/Table2[[#This Row],[Income]]) -> 2.7813314
A21: 2022-09 | B21: A302 | C21: =SUMIFS(Table1[FULL AMOUNT mxn pesos], Table1[Month], A21, Table1[APARTMENT], B21) -> 0 | D21: =SUMIFS(INCOME!C:C, INCOME!D:D, Table2[[#This Row],[Apt]], INCOME!J:J, Table2[[#This Row],[Month]]) -> 0 | E21: =SUMIFS(EXPENSES!$D:$D, EXPENSES!$C:$C, B21, EXPENSES!$F:$F, A21, EXPENSES!$E:$E, "Direct") -> 3550 | F21: =IF(C21=0,0,C21/SUMIF(A:A,A21,C:C)) -> 0 | G21: =SUMIFS(EXPENSES!D:D, EXPENSES!F:F, Data_Consolidado!A21, EXPENSES!E:E, "Shared") -> 7560.2 | H21: =Table2[[#This Row],[Shared_Total]]/3 -> 2520.0667 | I21: =E21+H21 -> 6070.0667 | J21: =C21-I21 -> -6070.0667 | K21: =IF(C21=0, "-", (J21/C21)) -> - | L21: =SUMIFS(Reference_Nights[[#All],[Available_nights]], Reference_Nights[[#All],[Month]], Table2[[#This Row],[Month]], Reference_Nights[[#All],[Apt]], Table2[[#This Row],[Apt]]) -> 27 | M21: =IF(Table2[[#This Row],[Available _Nights]]=0, 0, Table2[[#This Row],[Booked_Nights]]/Table2[[#This Row],[Available _Nights]]) -> 0 | N21: =IF(Table2[[#This Row],[Booked_Nights]]=0, 0, Table2[[#This Row],[Income]]/Table2[[#This Row],[Booked_Nights]]) -> 0 | O21: =IF(L21=0,0, Table2[[#This Row],[Income]]/Table2[[#This Row],[Available _Nights]]) -> 0 | P21: =IF(Table2[[#This Row],[Income]]=0,0,Table2[[#This Row],[Total_Exp]]/Table2[[#This Row],[Income]]) -> 0
A22: 2022-09 | B22: B303 | C22: =SUMIFS(Table1[FULL AMOUNT mxn pesos], Table1[Month], A22, Table1[APARTMENT], B22) -> 0 | D22: =SUMIFS(INCOME!C:C, INCOME!D:D, Table2[[#This Row],[Apt]], INCOME!J:J, Table2[[#This Row],[Month]]) -> 0 | E22: =SUMIFS(EXPENSES!$D:$D, EXPENSES!$C:$C, B22, EXPENSES!$F:$F, A22, EXPENSES!$E:$E, "Direct") -> 0 | F22: =IF(C22=0,0,C22/SUMIF(A:A,A22,C:C)) -> 0 | G22: =SUMIFS(EXPENSES!D:D, EXPENSES!F:F, Data_Consolidado!A22, EXPENSES!E:E, "Shared") -> 7560.2 | H22: =Table2[[#This Row],[Shared_Total]]/3 -> 2520.0667 | I22: =E22+H22 -> 2520.0667 | J22: =C22-I22 -> -2520.0667 | K22: =IF(C22=0, "-", (J22/C22)) -> - | L22: =SUMIFS(Reference_Nights[[#All],[Available_nights]], Reference_Nights[[#All],[Month]], Table2[[#This Row],[Month]], Reference_Nights[[#All],[Apt]], Table2[[#This Row],[Apt]]) -> 27 | M22: =IF(Table2[[#This Row],[Available _Nights]]=0, 0, Table2[[#This Row],[Booked_Nights]]/Table2[[#This Row],[Available _Nights]]) -> 0 | N22: =IF(Table2[[#This Row],[Booked_Nights]]=0, 0, Table2[[#This Row],[Income]]/Table2[[#This Row],[Booked_Nights]]) -> 0 | O22: =IF(L22=0,0, Table2[[#This Row],[Income]]/Table2[[#This Row],[Available _Nights]]) -> 0 | P22: =IF(Table2[[#This Row],[Income]]=0,0,Table2[[#This Row],[Total_Exp]]/Table2[[#This Row],[Income]]) -> 0
A23: 2022-09 | B23: C301 | C23: =SUMIFS(Table1[FULL AMOUNT mxn pesos], Table1[Month], A23, Table1[APARTMENT], B23) -> 0 | D23: =SUMIFS(INCOME!C:C, INCOME!D:D, Table2[[#This Row],[Apt]], INCOME!J:J, Table2[[#This Row],[Month]]) -> 0 | E23: =SUMIFS(EXPENSES!$D:$D, EXPENSES!$C:$C, B23, EXPENSES!$F:$F, A23, EXPENSES!$E:$E, "Direct") -> 1900 | F23: =IF(C23=0,0,C23/SUMIF(A:A,A23,C:C)) -> 0 | G23: =SUMIFS(EXPENSES!D:D, EXPENSES!F:F, Data_Consolidado!A23, EXPENSES!E:E, "Shared") -> 7560.2 | H23: =Table2[[#This Row],[Shared_Total]]/3 -> 2520.0667 | I23: =E23+H23 -> 4420.0667 | J23: =C23-I23 -> -4420.0667 | K23: =IF(C23=0, "-", (J23/C23)) -> - | L23: =SUMIFS(Reference_Nights[[#All],[Available_nights]], Reference_Nights[[#All],[Month]], Table2[[#This Row],[Month]], Reference_Nights[[#All],[Apt]], Table2[[#This Row],[Apt]]) -> 27 | M23: =IF(Table2[[#This Row],[Available _Nights]]=0, 0, Table2[[#This Row],[Booked_Nights]]/Table2[[#This Row],[Available _Nights]]) -> 0 | N23: =IF(Table2[[#This Row],[Booked_Nights]]=0, 0, Table2[[#This Row],[Income]]/Table2[[#This Row],[Booked_Nights]]) -> 0 | O23: =IF(L23=0,0, Table2[[#This Row],[Income]]/Table2[[#This Row],[Available _Nights]]) -> 0 | P23: =IF(Table2[[#This Row],[Income]]=0,0,Table2[[#This Row],[Total_Exp]]/Table2[[#This Row],[Income]]) -> 0
A24: 2022-10 | B24: A302 | C24: =SUMIFS(Table1[FULL AMOUNT mxn pesos], Table1[Month], A24, Table1[APARTMENT], B24) -> 18000 | D24: =SUMIFS(INCOME!C:C, INCOME!D:D, Table2[[#This Row],[Apt]], INCOME!J:J, Table2[[#This Row],[Month]]) -> 10 | E24: =SUMIFS(EXPENSES!$D:$D, EXPENSES!$C:$C, B24, EXPENSES!$F:$F, A24, EXPENSES!$E:$E, "Direct") -> 6267 | F24: =IF(C24=0,0,C24/SUMIF(A:A,A24,C:C)) -> 1 | G24: =SUMIFS(EXPENSES!D:D, EXPENSES!F:F, Data_Consolidado!A24, EXPENSES!E:E, "Shared") -> 15960 | H24: =G24*F24 -> 15960 | I24: =E24+H24 -> 22227 | J24: =C24-I24 -> -4227 | K24: =IF(C24=0, "-", (J24/C24)) -> -0.23483333 | L24: =SUMIFS(Reference_Nights[[#All],[Available_nights]], Reference_Nights[[#All],[Month]], Table2[[#This Row],[Month]], Reference_Nights[[#All],[Apt]], Table2[[#This Row],[Apt]]) -> 28 | M24: =IF(Table2[[#This Row],[Available _Nights]]=0, 0, Table2[[#This Row],[Booked_Nights]]/Table2[[#This Row],[Available _Nights]]) -> 0.35714286 | N24: =IF(Table2[[#This Row],[Booked_Nights]]=0, 0, Table2[[#This Row],[Income]]/Table2[[#This Row],[Booked_Nights]]) -> 1800 | O24: =IF(L24=0,0, Table2[[#This Row],[Income]]/Table2[[#This Row],[Available _Nights]]) -> 642.85714 | P24: =IF(Table2[[#This Row],[Income]]=0,0,Table2[[#This Row],[Total_Exp]]/Table2[[#This Row],[Income]]) -> 1.2348333
A25: 2022-10 | B25: B303 | C25: =SUMIFS(Table1[FULL AMOUNT mxn pesos], Table1[Month], A25, Table1[APARTMENT], B25) -> 0 | D25: =SUMIFS(INCOME!C:C, INCOME!D:D, Table2[[#This Row],[Apt]], INCOME!J:J, Table2[[#This Row],[Month]]) -> 0 | E25: =SUMIFS(EXPENSES!$D:$D, EXPENSES!$C:$C, B25, EXPENSES!$F:$F, A25, EXPENSES!$E:$E, "Direct") -> 700 | F25: =IF(C25=0,0,C25/SUMIF(A:A,A25,C:C)) -> 0 | G25: =SUMIFS(EXPENSES!D:D, EXPENSES!F:F, Data_Consolidado!A25, EXPENSES!E:E, "Shared") -> 15960 | H25: =G25*F25 -> 0 | I25: =E25+H25 -> 700 | J25: =C25-I25 -> -700 | K25: =IF(C25=0, "-", (J25/C25)) -> - | L25: =SUMIFS(Reference_Nights[[#All],[Available_nights]], Reference_Nights[[#All],[Month]], Table2[[#This Row],[Month]], Reference_Nights[[#All],[Apt]], Table2[[#This Row],[Apt]]) -> 28 | M25: =IF(Table2[[#This Row],[Available _Nights]]=0, 0, Table2[[#This Row],[Booked_Nights]]/Table2[[#This Row],[Available _Nights]]) -> 0 | N25: =IF(Table2[[#This Row],[Booked_Nights]]=0, 0, Table2[[#This Row],[Income]]/Table2[[#This Row],[Booked_Nights]]) -> 0 | O25: =IF(L25=0,0, Table2[[#This Row],[Income]]/Table2[[#This Row],[Available _Nights]]) -> 0 | P25: =IF(Table2[[#This Row],[Income]]=0,0,Table2[[#This Row],[Total_Exp]]/Table2[[#This Row],[Income]]) -> 0
A26: 2022-10 | B26: C301 | C26: =SUMIFS(Table1[FULL AMOUNT mxn pesos], Table1[Month], A26, Table1[APARTMENT], B26) -> 0 | D26: =SUMIFS(INCOME!C:C, INCOME!D:D, Table2[[#This Row],[Apt]], INCOME!J:J, Table2[[#This Row],[Month]]) -> 0 | E26: =SUMIFS(EXPENSES!$D:$D, EXPENSES!$C:$C, B26, EXPENSES!$F:$F, A26, EXPENSES!$E:$E, "Direct") -> 4200 | F26: =IF(C26=0,0,C26/SUMIF(A:A,A26,C:C)) -> 0 | G26: =SUMIFS(EXPENSES!D:D, EXPENSES!F:F, Data_Consolidado!A26, EXPENSES!E:E, "Shared") -> 15960 | H26: =G26*F26 -> 0 | I26: =E26+H26 -> 4200 | J26: =C26-I26 -> -4200 | K26: =IF(C26=0, "-", (J26/C26)) -> - | L26: =SUMIFS(Reference_Nights[[#All],[Available_nights]], Reference_Nights[[#All],[Month]], Table2[[#This Row],[Month]], Reference_Nights[[#All],[Apt]], Table2[[#This Row],[Apt]]) -> 28 | M26: =IF(Table2[[#This Row],[Available _Nights]]=0, 0, Table2[[#This Row],[Booked_Nights]]/Table2[[#This Row],[Available _Nights]]) -> 0 | N26: =IF(Table2[[#This Row],[Booked_Nights]]=0, 0, Table2[[#This Row],[Income]]/Table2[[#This Row],[Booked_Nights]]) -> 0 | O26: =IF(L26=0,0, Table2[[#This Row],[Income]]/Table2[[#This Row],[Available _Nights]]) -> 0 | P26: =IF(Table2[[#This Row],[Income]]=0,0,Table2[[#This Row],[Total_Exp]]/Table2[[#This Row],[Income]]) -> 0
A27: 2022-11 | B27: A302 | C27: =SUMIFS(Table1[FULL AMOUNT mxn pesos], Table1[Month], A27, Table1[APARTMENT], B27) -> 49329.6 | D27: =SUMIFS(INCOME!C:C, INCOME!D:D, Table2[[#This Row],[Apt]], INCOME!J:J, Table2[[#This Row],[Month]]) -> 26 | E27: =SUMIFS(EXPENSES!$D:$D, EXPENSES!$C:$C, B27, EXPENSES!$F:$F, A27, EXPENSES!$E:$E, "Direct") -> 11600 | F27: =IF(C27=0,0,C27/SUMIF(A:A,A27,C:C)) -> 0.67306307 | G27: =SUMIFS(EXPENSES!D:D, EXPENSES!F:F, Data_Consolidado!A27, EXPENSES!E:E, "Shared") -> 38209 | H27: =G27*F27 -> 25717.067 | I27: =E27+H27 -> 37317.067 | J27: =C27-I27 -> 12012.533 | K27: =IF(C27=0, "-", (J27/C27)) -> 0.24351572 | L27: =SUMIFS(Reference_Nights[[#All],[Available_nights]], Reference_Nights[[#All],[Month]], Table2[[#This Row],[Month]], Reference_Nights[[#All],[Apt]], Table2[[#This Row],[Apt]]) -> 27 | M27: =IF(Table2[[#This Row],[Available _Nights]]=0, 0, Table2[[#This Row],[Booked_Nights]]/Table2[[#This Row],[Available _Nights]]) -> 0.96296296 | N27: =IF(Table2[[#This Row],[Booked_Nights]]=0, 0, Table2[[#This Row],[Income]]/Table2[[#This Row],[Booked_Nights]]) -> 1897.2923 | O27: =IF(L27=0,0, Table2[[#This Row],[Income]]/Table2[[#This Row],[Available _Nights]]) -> 1827.0222 | P27: =IF(Table2[[#This Row],[Income]]=0,0,Table2[[#This Row],[Total_Exp]]/Table2[[#This Row],[Income]]) -> 0.75648428
A28: 2022-11 | B28: B303 | C28: =SUMIFS(Table1[FULL AMOUNT mxn pesos], Table1[Month], A28, Table1[APARTMENT], B28) -> 12300 | D28: =SUMIFS(INCOME!C:C, INCOME!D:D, Table2[[#This Row],[Apt]], INCOME!J:J, Table2[[#This Row],[Month]]) -> 6 | E28: =SUMIFS(EXPENSES!$D:$D, EXPENSES!$C:$C, B28, EXPENSES!$F:$F, A28, EXPENSES!$E:$E, "Direct") -> 4470 | F28: =IF(C28=0,0,C28/SUMIF(A:A,A28,C:C)) -> 0.1678237 | G28: =SUMIFS(EXPENSES!D:D, EXPENSES!F:F, Data_Consolidado!A28, EXPENSES!E:E, "Shared") -> 38209 | H28: =G28*F28 -> 6412.3756 | I28: =E28+H28 -> 10882.376 | J28: =C28-I28 -> 1417.6244 | K28: =IF(C28=0, "-", (J28/C28)) -> 0.11525402 | L28: =SUMIFS(Reference_Nights[[#All],[Available_nights]], Reference_Nights[[#All],[Month]], Table2[[#This Row],[Month]], Reference_Nights[[#All],[Apt]], Table2[[#This Row],[Apt]]) -> 27 | M28: =IF(Table2[[#This Row],[Available _Nights]]=0, 0, Table2[[#This Row],[Booked_Nights]]/Table2[[#This Row],[Available _Nights]]) -> 0.22222222 | N28: =IF(Table2[[#This Row],[Booked_Nights]]=0, 0, Table2[[#This Row],[Income]]/Table2[[#This Row],[Booked_Nights]]) -> 2050 | O28: =IF(L28=0,0, Table2[[#This Row],[Income]]/Table2[[#This Row],[Available _Nights]]) -> 455.55556 | P28: =IF(Table2[[#This Row],[Income]]=0,0,Table2[[#This Row],[Total_Exp]]/Table2[[#This Row],[Income]]) -> 0.88474598
A29: 2022-11 | B29: C301 | C29: =SUMIFS(Table1[FULL AMOUNT mxn pesos], Table1[Month], A29, Table1[APARTMENT], B29) -> 11661.6 | D29: =SUMIFS(INCOME!C:C, INCOME!D:D, Table2[[#This Row],[Apt]], INCOME!J:J, Table2[[#This Row],[Month]]) -> 8 | E29: =SUMIFS(EXPENSES!$D:$D, EXPENSES!$C:$C, B29, EXPENSES!$F:$F, A29, EXPENSES!$E:$E, "Direct") -> 23842 | F29: =IF(C29=0,0,C29/SUMIF(A:A,A29,C:C)) -> 0.15911324 | G29: =SUMIFS(EXPENSES!D:D, EXPENSES!F:F, Data_Consolidado!A29, EXPENSES!E:E, "Shared") -> 38209 | H29: =G29*F29 -> 6079.5576 | I29: =E29+H29 -> 29921.558 | J29: =C29-I29 -> -18259.958 | K29: =IF(C29=0, "-", (J29/C29)) -> -1.5658192 | L29: =SUMIFS(Reference_Nights[[#All],[Available_nights]], Reference_Nights[[#All],[Month]], Table2[[#This Row],[Month]], Reference_Nights[[#All],[Apt]], Table2[[#This Row],[Apt]]) -> 27 | M29: =IF(Table2[[#This Row],[Available _Nights]]=0, 0, Table2[[#This Row],[Booked_Nights]]/Table2[[#This Row],[Available _Nights]]) -> 0.2962963 | N29: =IF(Table2[[#This Row],[Booked_Nights]]=0, 0, Table2[[#This Row],[Income]]/Table2[[#This Row],[Booked_Nights]]) -> 1457.7 | O29: =IF(L29=0,0, Table2[[#This Row],[Income]]/Table2[[#This Row],[Available _Nights]]) -> 431.91111 | P29: =IF(Table2[[#This Row],[Income]]=0,0,Table2[[#This Row],[Total_Exp]]/Table2[[#This Row],[Income]]) -> 2.5658192
A30: 2022-12 | B30: A302 | C30: =SUMIFS(Table1[FULL AMOUNT mxn pesos], Table1[Month], A30, Table1[APARTMENT], B30) -> 56866.6 | D30: =SUMIFS(INCOME!C:C, INCOME!D:D, Table2[[#This Row],[Apt]], INCOME!J:J, Table2[[#This Row],[Month]]) -> 16 | E30: =SUMIFS(EXPENSES!$D:$D, EXPENSES!$C:$C, B30, EXPENSES!$F:$F, A30, EXPENSES!$E:$E, "Direct") -> 16310 | F30: =IF(C30=0,0,C30/SUMIF(A:A,A30,C:C)) -> 0.29099147 | G30: =SUMIFS(EXPENSES!D:D, EXPENSES!F:F, Data_Consolidado!A30, EXPENSES!E:E, "Shared") -> 22700 | H30: =G30*F30 -> 6605.5063 | I30: =E30+H30 -> 22915.506 | J30: =C30-I30 -> 33951.094 | K30: =IF(C30=0, "-", (J30/C30)) -> 0.59703048 | L30: =SUMIFS(Reference_Nights[[#All],[Available_nights]], Reference_Nights[[#All],[Month]], Table2[[#This Row],[Month]], Reference_Nights[[#All],[Apt]], Table2[[#This Row],[Apt]]) -> 28 | M30: =IF(Table2[[#This Row],[Available _Nights]]=0, 0, Table2[[#This Row],[Booked_Nights]]/Table2[[#This Row],[Available _Nights]]) -> 0.57142857 | N30: =IF(Table2[[#This Row],[Booked_Nights]]=0, 0, Table2[[#This Row],[Income]]/Table2[[#This Row],[Booked_Nights]]) -> 3554.1625 | O30: =IF(L30=0,0, Table2[[#This Row],[Income]]/Table2[[#This Row],[Available _Nights]]) -> 2030.95 | P30: =IF(Table2[[#This Row],[Income]]=0,0,Table2[[#This Row],[Total_Exp]]/Table2[[#This Row],[Income]]) -> 0.40296952
A31: 2022-12 | B31: B303 | C31: =SUMIFS(Table1[FULL AMOUNT mxn pesos], Table1[Month], A31, Table1[APARTMENT], B31) -> 74357 | D31: =SUMIFS(INCOME!C:C, INCOME!D:D, Table2[[#This Row],[Apt]], INCOME!J:J, Table2[[#This Row],[Month]]) -> 19 | E31: =SUMIFS(EXPENSES!$D:$D, EXPENSES!$C:$C, B31, EXPENSES!$F:$F, A31, EXPENSES!$E:$E, "Direct") -> 7460 | F31: =IF(C31=0,0,C31/SUMIF(A:A,A31,C:C)) -> 0.3804914 | G31: =SUMIFS(EXPENSES!D:D, EXPENSES!F:F, Data_Consolidado!A31, EXPENSES!E:E, "Shared") -> 22700 | H31: =G31*F31 -> 8637.1549 | I31: =E31+H31 -> 16097.155 | J31: =C31-I31 -> 58259.845 | K31: =IF(C31=0, "-", (J31/C31)) -> 0.78351527 | L31: =SUMIFS(Reference_Nights[[#All],[Available_nights]], Reference_Nights[[#All],[Month]], Table2[[#This Row],[Month]], Reference_Nights[[#All],[Apt]], Table2[[#This Row],[Apt]]) -> 28 | M31: =IF(Table2[[#This Row],[Available _Nights]]=0, 0, Table2[[#This Row],[Booked_Nights]]/Table2[[#This Row],[Available _Nights]]) -> 0.67857143 | N31: =IF(Table2[[#This Row],[Booked_Nights]]=0, 0, Table2[[#This Row],[Income]]/Table2[[#This Row],[Booked_Nights]]) -> 3913.5263 | O31: =IF(L31=0,0, Table2[[#This Row],[Income]]/Table2[[#This Row],[Available _Nights]]) -> 2655.6071 | P31: =IF(Table2[[#This Row],[Income]]=0,0,Table2[[#This Row],[Total_Exp]]/Table2[[#This Row],[Income]]) -> 0.21648473
A32: 2022-12 | B32: C301 | C32: =SUMIFS(Table1[FULL AMOUNT mxn pesos], Table1[Month], A32, Table1[APARTMENT], B32) -> 64200 | D32: =SUMIFS(INCOME!C:C, INCOME!D:D, Table2[[#This Row],[Apt]], INCOME!J:J, Table2[[#This Row],[Month]]) -> 42 | E32: =SUMIFS(EXPENSES!$D:$D, EXPENSES!$C:$C, B32, EXPENSES!$F:$F, A32, EXPENSES!$E:$E, "Direct") -> 7490 | F32: =IF(C32=0,0,C32/SUMIF(A:A,A32,C:C)) -> 0.32851713 | G32: =SUMIFS(EXPENSES!D:D, EXPENSES!F:F, Data_Consolidado!A32, EXPENSES!E:E, "Shared") -> 22700 | H32: =G32*F32 -> 7457.3388 | I32: =E32+H32 -> 14947.339 | J32: =C32-I32 -> 49252.661 | K32: =IF(C32=0, "-", (J32/C32)) -> 0.76717541 | L32: =SUMIFS(Reference_Nights[[#All],[Available_nights]], Reference_Nights[[#All],[Month]], Table2[[#This Row],[Month]], Reference_Nights[[#All],[Apt]], Table2[[#This Row],[Apt]]) -> 28 | M32: =IF(Table2[[#This Row],[Available _Nights]]=0, 0, Table2[[#This Row],[Booked_Nights]]/Table2[[#This Row],[Available _Nights]]) -> 1.5 | N32: =IF(Table2[[#This Row],[Booked_Nights]]=0, 0, Table2[[#This Row],[Income]]/Table2[[#This Row],[Booked_Nights]]) -> 1528.5714 | O32: =IF(L32=0,0, Table2[[#This Row],[Income]]/Table2[[#This Row],[Available _Nights]]) -> 2292.8571 | P32: =IF(Table2[[#This Row],[Income]]=0,0,Table2[[#This Row],[Total_Exp]]/Table2[[#This Row],[Income]]) -> 0.23282459
A33: 2023-01 | B33: A302 | C33: =SUMIFS(Table1[FULL AMOUNT mxn pesos], Table1[Month], A33, Table1[APARTMENT], B33) -> 127716.4 | D33: =SUMIFS(INCOME!C:C, INCOME!D:D, Table2[[#This Row],[Apt]], INCOME!J:J, Table2[[#This Row],[Month]]) -> 43 | E33: =SUMIFS(EXPENSES!$D:$D, EXPENSES!$C:$C, B33, EXPENSES!$F:$F, A33, EXPENSES!$E:$E, "Direct") -> 24790 | F33: =IF(C33=0,0,C33/SUMIF(A:A,A33,C:C)) -> 0.53977007 | G33: =SUMIFS(EXPENSES!D:D, EXPENSES!F:F, Data_Consolidado!A33, EXPENSES!E:E, "Shared") -> 11670 | H33: =G33*F33 -> 6299.1167 | I33: =E33+H33 -> 31089.117 | J33: =C33-I33 -> 96627.283 | K33: =IF(C33=0, "-", (J33/C33)) -> 0.75657694 | L33: =SUMIFS(Reference_Nights[[#All],[Available_nights]], Reference_Nights[[#All],[Month]], Table2[[#This Row],[Month]], Reference_Nights[[#All],[Apt]], Table2[[#This Row],[Apt]]) -> 28 | M33: =IF(Table2[[#This Row],[Available _Nights]]=0, 0, Table2[[#This Row],[Booked_Nights]]/Table2[[#This Row],[Available _Nights]]) -> 1.5357143 | N33: =IF(Table2[[#This Row],[Booked_Nights]]=0, 0, Table2[[#This Row],[Income]]/Table2[[#This Row],[Booked_Nights]]) -> 2970.1488 | O33: =IF(L33=0,0, Table2[[#This Row],[Income]]/Table2[[#This Row],[Available _Nights]]) -> 4561.3 | P33: =IF(Table2[[#This Row],[Income]]=0,0,Table2[[#This Row],[Total_Exp]]/Table2[[#This Row],[Income]]) -> 0.24342306
A34: 2023-01 | B34: B303 | C34: =SUMIFS(Table1[FULL AMOUNT mxn pesos], Table1[Month], A34, Table1[APARTMENT], B34) -> 36306.6 | D34: =SUMIFS(INCOME!C:C, INCOME!D:D, Table2[[#This Row],[Apt]], INCOME!J:J, Table2[[#This Row],[Month]]) -> 13 | E34: =SUMIFS(EXPENSES!$D:$D, EXPENSES!$C:$C, B34, EXPENSES!$F:$F, A34, EXPENSES!$E:$E, "Direct") -> 14670 | F34: =IF(C34=0,0,C34/SUMIF(A:A,A34,C:C)) -> 0.15344322 | G34: =SUMIFS(EXPENSES!D:D, EXPENSES!F:F, Data_Consolidado!A34, EXPENSES!E:E, "Shared") -> 11670 | H34: =G34*F34 -> 1790.6824 | I34: =E34+H34 -> 16460.682 | J34: =C34-I34 -> 19845.918 | K34: =IF(C34=0, "-", (J34/C34)) -> 0.54662011 | L34: =SUMIFS(Reference_Nights[[#All],[Available_nights]], Reference_Nights[[#All],[Month]], Table2[[#This Row],[Month]], Reference_Nights[[#All],[Apt]], Table2[[#This Row],[Apt]]) -> 28 | M34: =IF(Table2[[#This Row],[Available _Nights]]=0, 0, Table2[[#This Row],[Booked_Nights]]/Table2[[#This Row],[Available _Nights]]) -> 0.46428571 | N34: =IF(Table2[[#This Row],[Booked_Nights]]=0, 0, Table2[[#This Row],[Income]]/Table2[[#This Row],[Booked_Nights]]) -> 2792.8154 | O34: =IF(L34=0,0, Table2[[#This Row],[Income]]/Table2[[#This Row],[Available _Nights]]) -> 1296.6643 | P34: =IF(Table2[[#This Row],[Income]]=0,0,Table2[[#This Row],[Total_Exp]]/Table2[[#This Row],[Income]]) -> 0.45337989
A35: 2023-01 | B35: C301 | C35: =SUMIFS(Table1[FULL AMOUNT mxn pesos], Table1[Month], A35, Table1[APARTMENT], B35) -> 72589.6 | D35: =SUMIFS(INCOME!C:C, INCOME!D:D, Table2[[#This Row],[Apt]], INCOME!J:J, Table2[[#This Row],[Month]]) -> 22 | E35: =SUMIFS(EXPENSES!$D:$D, EXPENSES!$C:$C, B35, EXPENSES!$F:$F, A35, EXPENSES!$E:$E, "Direct") -> 17390 | F35: =IF(C35=0,0,C35/SUMIF(A:A,A35,C:C)) -> 0.30678671 | G35: =SUMIFS(EXPENSES!D:D, EXPENSES!F:F, Data_Consolidado!A35, EXPENSES!E:E, "Shared") -> 11670 | H35: =G35*F35 -> 3580.2009 | I35: =E35+H35 -> 20970.201 | J35: =C35-I35 -> 51619.399 | K35: =IF(C35=0, "-", (J35/C35)) -> 0.71111287 | L35: =SUMIFS(Reference_Nights[[#All],[Available_nights]], Reference_Nights[[#All],[Month]], Table2[[#This Row],[Month]], Reference_Nights[[#All],[Apt]], Table2[[#This Row],[Apt]]) -> 28 | M35: =IF(Table2[[#This Row],[Available _Nights]]=0, 0, Table2[[#This Row],[Booked_Nights]]/Table2[[#This Row],[Available _Nights]]) -> 0.78571429 | N35: =IF(Table2[[#This Row],[Booked_Nights]]=0, 0, Table2[[#This Row],[Income]]/Table2[[#This Row],[Booked_Nights]]) -> 3299.5273 | O35: =IF(L35=0,0, Table2[[#This Row],[Income]]/Table2[[#This Row],[Available _Nights]]) -> 2592.4857 | P35: =IF(Table2[[#This Row],[Income]]=0,0,Table2[[#This Row],[Total_Exp]]/Table2[[#This Row],[Income]]) -> 0.28888713
... A53: 2023-07 | B53: C301 | C53: =SUMIFS(Table1[FULL AMOUNT mxn pesos], Table1[Month], A53, Table1[APARTMENT], B53) -> 0 | D53: =SUMIFS(INCOME!C:C, INCOME!D:D, Table2[[#This Row],[Apt]], INCOME!J:J, Table2[[#This Row],[Month]]) -> 0 | E53: =SUMIFS(EXPENSES!$D:$D, EXPENSES!$C:$C, B53, EXPENSES!$F:$F, A53, EXPENSES!$E:$E, "Direct") -> 20000 | F53: =IF(C53=0,0,C53/SUMIF(A:A,A53,C:C)) -> 0 | G53: =SUMIFS(EXPENSES!D:D, EXPENSES!F:F, Data_Consolidado!A53, EXPENSES!E:E, "Shared") -> 2300 | H53: =G53*F53 -> 0 | I53: =E53+H53 -> 20000 | J53: =C53-I53 -> -20000 | K53: =IF(C53=0, "-", (J53/C53)) -> - | L53: =SUMIFS(Reference_Nights[[#All],[Available_nights]], Reference_Nights[[#All],[Month]], Table2[[#This Row],[Month]], Reference_Nights[[#All],[Apt]], Table2[[#This Row],[Apt]]) -> 28 | M53: =IF(Table2[[#This Row],[Available _Nights]]=0, 0, Table2[[#This Row],[Booked_Nights]]/Table2[[#This Row],[Available _Nights]]) -> 0 | N53: =IF(Table2[[#This Row],[Booked_Nights]]=0, 0, Table2[[#This Row],[Income]]/Table2[[#This Row],[Booked_Nights]]) -> 0 | O53: =IF(L53=0,0, Table2[[#This Row],[Income]]/Table2[[#This Row],[Available _Nights]]) -> 0 | P53: =IF(Table2[[#This Row],[Income]]=0,0,Table2[[#This Row],[Total_Exp]]/Table2[[#This Row],[Income]]) -> 0
A54: 2023-08 | B54: A302 | C54: =SUMIFS(Table1[FULL AMOUNT mxn pesos], Table1[Month], A54, Table1[APARTMENT], B54) -> 0 | D54: =SUMIFS(INCOME!C:C, INCOME!D:D, Table2[[#This Row],[Apt]], INCOME!J:J, Table2[[#This Row],[Month]]) -> 0 | E54: =SUMIFS(EXPENSES!$D:$D, EXPENSES!$C:$C, B54, EXPENSES!$F:$F, A54, EXPENSES!$E:$E, "Direct") -> 37550 | F54: =IF(C54=0,0,C54/SUMIF(A:A,A54,C:C)) -> 0 | G54: =SUMIFS(EXPENSES!D:D, EXPENSES!F:F, Data_Consolidado!A54, EXPENSES!E:E, "Shared") -> 8945 | H54: =Table2[[#This Row],[Shared_Total]]/3 -> 2981.6667 | I54: =E54+H54 -> 40531.667 | J54: =C54-I54 -> -40531.667 | K54: =IF(C54=0, "-", (J54/C54)) -> - | L54: =SUMIFS(Reference_Nights[[#All],[Available_nights]], Reference_Nights[[#All],[Month]], Table2[[#This Row],[Month]], Reference_Nights[[#All],[Apt]], Table2[[#This Row],[Apt]]) -> 28 | M54: =IF(Table2[[#This Row],[Available _Nights]]=0, 0, Table2[[#This Row],[Booked_Nights]]/Table2[[#This Row],[Available _Nights]]) -> 0 | N54: =IF(Table2[[#This Row],[Booked_Nights]]=0, 0, Table2[[#This Row],[Income]]/Table2[[#This Row],[Booked_Nights]]) -> 0 | O54: =IF(L54=0,0, Table2[[#This Row],[Income]]/Table2[[#This Row],[Available _Nights]]) -> 0 | P54: =IF(Table2[[#This Row],[Income]]=0,0,Table2[[#This Row],[Total_Exp]]/Table2[[#This Row],[Income]]) -> 0
A55: 2023-08 | B55: B303 | C55: =SUMIFS(Table1[FULL AMOUNT mxn pesos], Table1[Month], A55, Table1[APARTMENT], B55) -> 0 | D55: =SUMIFS(INCOME!C:C, INCOME!D:D, Table2[[#This Row],[Apt]], INCOME!J:J, Table2[[#This Row],[Month]]) -> 0 | E55: =SUMIFS(EXPENSES!$D:$D, EXPENSES!$C:$C, B55, EXPENSES!$F:$F, A55, EXPENSES!$E:$E, "Direct") -> 25000 | F55: =IF(C55=0,0,C55/SUMIF(A:A,A55,C:C)) -> 0 | G55: =SUMIFS(EXPENSES!D:D, EXPENSES!F:F, Data_Consolidado!A55, EXPENSES!E:E, "Shared") -> 8945 | H55: =Table2[[#This Row],[Shared_Total]]/3 -> 2981.6667 | I55: =E55+H55 -> 27981.667 | J55: =C55-I55 -> -27981.667 | K55: =IF(C55=0, "-", (J55/C55)) -> - | L55: =SUMIFS(Reference_Nights[[#All],[Available_nights]], Reference_Nights[[#All],[Month]], Table2[[#This Row],[Month]], Reference_Nights[[#All],[Apt]], Table2[[#This Row],[Apt]]) -> 28 | M55: =IF(Table2[[#This Row],[Available _Nights]]=0, 0, Table2[[#This Row],[Booked_Nights]]/Table2[[#This Row],[Available _Nights]]) -> 0 | N55: =IF(Table2[[#This Row],[Booked_Nights]]=0, 0, Table2[[#This Row],[Income]]/Table2[[#This Row],[Booked_Nights]]) -> 0 | O55: =IF(L55=0,0, Table2[[#This Row],[Income]]/Table2[[#This Row],[Available _Nights]]) -> 0 | P55: =IF(Table2[[#This Row],[Income]]=0,0,Table2[[#This Row],[Total_Exp]]/Table2[[#This Row],[Income]]) -> 0
A56: 2023-08 | B56: C301 | C56: =SUMIFS(Table1[FULL AMOUNT mxn pesos], Table1[Month], A56, Table1[APARTMENT], B56) -> 0 | D56: =SUMIFS(INCOME!C:C, INCOME!D:D, Table2[[#This Row],[Apt]], INCOME!J:J, Table2[[#This Row],[Month]]) -> 0 | E56: =SUMIFS(EXPENSES!$D:$D, EXPENSES!$C:$C, B56, EXPENSES!$F:$F, A56, EXPENSES!$E:$E, "Direct") -> 30000 | F56: =IF(C56=0,0,C56/SUMIF(A:A,A56,C:C)) -> 0 | G56: =SUMIFS(EXPENSES!D:D, EXPENSES!F:F, Data_Consolidado!A56, EXPENSES!E:E, "Shared") -> 8945 | H56: =Table2[[#This Row],[Shared_Total]]/3 -> 2981.6667 | I56: =E56+H56 -> 32981.667 | J56: =C56-I56 -> -32981.667 | K56: =IF(C56=0, "-", (J56/C56)) -> - | L56: =SUMIFS(Reference_Nights[[#All],[Available_nights]], Reference_Nights[[#All],[Month]], Table2[[#This Row],[Month]], Reference_Nights[[#All],[Apt]], Table2[[#This Row],[Apt]]) -> 28 | M56: =IF(Table2[[#This Row],[Available _Nights]]=0, 0, Table2[[#This Row],[Booked_Nights]]/Table2[[#This Row],[Available _Nights]]) -> 0 | N56: =IF(Table2[[#This Row],[Booked_Nights]]=0, 0, Table2[[#This Row],[Income]]/Table2[[#This Row],[Booked_Nights]]) -> 0 | O56: =IF(L56=0,0, Table2[[#This Row],[Income]]/Table2[[#This Row],[Available _Nights]]) -> 0 | P56: =IF(Table2[[#This Row],[Income]]=0,0,Table2[[#This Row],[Total_Exp]]/Table2[[#This Row],[Income]]) -> 0
A57: 2023-09 | B57: A302 | C57: =SUMIFS(Table1[FULL AMOUNT mxn pesos], Table1[Month], A57, Table1[APARTMENT], B57) -> 4760 | D57: =SUMIFS(INCOME!C:C, INCOME!D:D, Table2[[#This Row],[Apt]], INCOME!J:J, Table2[[#This Row],[Month]]) -> 4 | E57: =SUMIFS(EXPENSES!$D:$D, EXPENSES!$C:$C, B57, EXPENSES!$F:$F, A57, EXPENSES!$E:$E, "Direct") -> 40460 | F57: =IF(C57=0,0,C57/SUMIF(A:A,A57,C:C)) -> 0.034303834 | G57: =SUMIFS(EXPENSES!D:D, EXPENSES!F:F, Data_Consolidado!A57, EXPENSES!E:E, "Shared") -> 18038 | H57: =G57*F57 -> 618.77256 | I57: =E57+H57 -> 41078.773 | J57: =C57-I57 -> -36318.773 | K57: =IF(C57=0, "-", (J57/C57)) -> -7.6299942 | L57: =SUMIFS(Reference_Nights[[#All],[Available_nights]], Reference_Nights[[#All],[Month]], Table2[[#This Row],[Month]], Reference_Nights[[#All],[Apt]], Table2[[#This Row],[Apt]]) -> 27 | M57: =IF(Table2[[#This Row],[Available _Nights]]=0, 0, Table2[[#This Row],[Booked_Nights]]/Table2[[#This Row],[Available _Nights]]) -> 0.14814815 | N57: =IF(Table2[[#This Row],[Booked_Nights]]=0, 0, Table2[[#This Row],[Income]]/Table2[[#This Row],[Booked_Nights]]) -> 1190 | O57: =IF(L57=0,0, Table2[[#This Row],[Income]]/Table2[[#This Row],[Available _Nights]]) -> 176.2963 | P57: =IF(Table2[[#This Row],[Income]]=0,0,Table2[[#This Row],[Total_Exp]]/Table2[[#This Row],[Income]]) -> 8.6299942
A58: 2023-09 | B58: B303 | C58: =SUMIFS(Table1[FULL AMOUNT mxn pesos], Table1[Month], A58, Table1[APARTMENT], B58) -> 134000 | D58: =SUMIFS(INCOME!C:C, INCOME!D:D, Table2[[#This Row],[Apt]], INCOME!J:J, Table2[[#This Row],[Month]]) -> 2 | E58: =SUMIFS(EXPENSES!$D:$D, EXPENSES!$C:$C, B58, EXPENSES!$F:$F, A58, EXPENSES!$E:$E, "Direct") -> 21050 | F58: =IF(C58=0,0,C58/SUMIF(A:A,A58,C:C)) -> 0.96569617 | G58: =SUMIFS(EXPENSES!D:D, EXPENSES!F:F, Data_Consolidado!A58, EXPENSES!E:E, "Shared") -> 18038 | H58: =G58*F58 -> 17419.227 | I58: =E58+H58 -> 38469.227 | J58: =C58-I58 -> 95530.773 | K58: =IF(C58=0, "-", (J58/C58)) -> 0.71291621 | L58: =SUMIFS(Reference_Nights[[#All],[Available_nights]], Reference_Nights[[#All],[Month]], Table2[[#This Row],[Month]], Reference_Nights[[#All],[Apt]], Table2[[#This Row],[Apt]]) -> 27 | M58: =IF(Table2[[#This Row],[Available _Nights]]=0, 0, Table2[[#This Row],[Booked_Nights]]/Table2[[#This Row],[Available _Nights]]) -> 0.074074074 | N58: =IF(Table2[[#This Row],[Booked_Nights]]=0, 0, Table2[[#This Row],[Income]]/Table2[[#This Row],[Booked_Nights]]) -> 67000 | O58: =IF(L58=0,0, Table2[[#This Row],[Income]]/Table2[[#This Row],[Available _Nights]]) -> 4962.963 | P58: =IF(Table2[[#This Row],[Income]]=0,0,Table2[[#This Row],[Total_Exp]]/Table2[[#This Row],[Income]]) -> 0.28708379
A59: 2023-09 | B59: C301 | C59: =SUMIFS(Table1[FULL AMOUNT mxn pesos], Table1[Month], A59, Table1[APARTMENT], B59) -> 0 | D59: =SUMIFS(INCOME!C:C, INCOME!D:D, Table2[[#This Row],[Apt]], INCOME!J:J, Table2[[#This Row],[Month]]) -> 0 | E59: =SUMIFS(EXPENSES!$D:$D, EXPENSES!$C:$C, B59, EXPENSES!$F:$F, A59, EXPENSES!$E:$E, "Direct") -> 43820 | F59: =IF(C59=0,0,C59/SUMIF(A:A,A59,C:C)) -> 0 | G59: =SUMIFS(EXPENSES!D:D, EXPENSES!F:F, Data_Consolidado!A59, EXPENSES!E:E, "Shared") -> 18038 | H59: =G59*F59 -> 0 | I59: =E59+H59 -> 43820 | J59: =C59-I59 -> -43820 | K59: =IF(C59=0, "-", (J59/C59)) -> - | L59: =SUMIFS(Reference_Nights[[#All],[Available_nights]], Reference_Nights[[#All],[Month]], Table2[[#This Row],[Month]], Reference_Nights[[#All],[Apt]], Table2[[#This Row],[Apt]]) -> 27 | M59: =IF(Table2[[#This Row],[Available _Nights]]=0, 0, Table2[[#This Row],[Booked_Nights]]/Table2[[#This Row],[Available _Nights]]) -> 0 | N59: =IF(Table2[[#This Row],[Booked_Nights]]=0, 0, Table2[[#This Row],[Income]]/Table2[[#This Row],[Booked_Nights]]) -> 0 | O59: =IF(L59=0,0, Table2[[#This Row],[Income]]/Table2[[#This Row],[Available _Nights]]) -> 0 | P59: =IF(Table2[[#This Row],[Income]]=0,0,Table2[[#This Row],[Total_Exp]]/Table2[[#This Row],[Income]]) -> 0
A60: 2023-10 | B60: A302 | C60: =SUMIFS(Table1[FULL AMOUNT mxn pesos], Table1[Month], A60, Table1[APARTMENT], B60) -> 17400 | D60: =SUMIFS(INCOME!C:C, INCOME!D:D, Table2[[#This Row],[Apt]], INCOME!J:J, Table2[[#This Row],[Month]]) -> 11 | E60: =SUMIFS(EXPENSES!$D:$D, EXPENSES!$C:$C, B60, EXPENSES!$F:$F, A60, EXPENSES!$E:$E, "Direct") -> 44250 | F60: =IF(C60=0,0,C60/SUMIF(A:A,A60,C:C)) -> 0.10405454 | G60: =SUMIFS(EXPENSES!D:D, EXPENSES!F:F, Data_Consolidado!A60, EXPENSES!E:E, "Shared") -> 13055 | H60: =G60*F60 -> 1358.432 | I60: =E60+H60 -> 45608.432 | J60: =C60-I60 -> -28208.432 | K60: =IF(C60=0, "-", (J60/C60)) -> -1.6211743 | L60: =SUMIFS(Reference_Nights[[#All],[Available_nights]], Reference_Nights[[#All],[Month]], Table2[[#This Row],[Month]], Reference_Nights[[#All],[Apt]], Table2[[#This Row],[Apt]]) -> 28 | M60: =IF(Table2[[#This Row],[Available _Nights]]=0, 0, Table2[[#This Row],[Booked_Nights]]/Table2[[#This Row],[Available _Nights]]) -> 0.39285714 | N60: =IF(Table2[[#This Row],[Booked_Nights]]=0, 0, Table2[[#This Row],[Income]]/Table2[[#This Row],[Booked_Nights]]) -> 1581.8182 | O60: =IF(L60=0,0, Table2[[#This Row],[Income]]/Table2[[#This Row],[Available _Nights]]) -> 621.42857 | P60: =IF(Table2[[#This Row],[Income]]=0,0,Table2[[#This Row],[Total_Exp]]/Table2[[#This Row],[Income]]) -> 2.6211743
A61: 2023-10 | B61: B303 | C61: =SUMIFS(Table1[FULL AMOUNT mxn pesos], Table1[Month], A61, Table1[APARTMENT], B61) -> 0 | D61: =SUMIFS(INCOME!C:C, INCOME!D:D, Table2[[#This Row],[Apt]], INCOME!J:J, Table2[[#This Row],[Month]]) -> 0 | E61: =SUMIFS(EXPENSES!$D:$D, EXPENSES!$C:$C, B61, EXPENSES!$F:$F, A61, EXPENSES!$E:$E, "Direct") -> 19000 | F61: =IF(C61=0,0,C61/SUMIF(A:A,A61,C:C)) -> 0 | G61: =SUMIFS(EXPENSES!D:D, EXPENSES!F:F, Data_Consolidado!A61, EXPENSES!E:E, "Shared") -> 13055 | H61: =G61*F61 -> 0 | I61: =E61+H61 -> 19000 | J61: =C61-I61 -> -19000 | K61: =IF(C61=0, "-", (J61/C61)) -> - | L61: =SUMIFS(Reference_Nights[[#All],[Available_nights]], Reference_Nights[[#All],[Month]], Table2[[#This Row],[Month]], Reference_Nights[[#All],[Apt]], Table2[[#This Row],[Apt]]) -> 28 | M61: =IF(Table2[[#This Row],[Available _Nights]]=0, 0, Table2[[#This Row],[Booked_Nights]]/Table2[[#This Row],[Available _Nights]]) -> 0 | N61: =IF(Table2[[#This Row],[Booked_Nights]]=0, 0, Table2[[#This Row],[Income]]/Table2[[#This Row],[Booked_Nights]]) -> 0 | O61: =IF(L61=0,0, Table2[[#This Row],[Income]]/Table2[[#This Row],[Available _Nights]]) -> 0 | P61: =IF(Table2[[#This Row],[Income]]=0,0,Table2[[#This Row],[Total_Exp]]/Table2[[#This Row],[Income]]) -> 0
A62: 2023-10 | B62: C301 | C62: =SUMIFS(Table1[FULL AMOUNT mxn pesos], Table1[Month], A62, Table1[APARTMENT], B62) -> 149820 | D62: =SUMIFS(INCOME!C:C, INCOME!D:D, Table2[[#This Row],[Apt]], INCOME!J:J, Table2[[#This Row],[Month]]) -> 11 | E62: =SUMIFS(EXPENSES!$D:$D, EXPENSES!$C:$C, B62, EXPENSES!$F:$F, A62, EXPENSES!$E:$E, "Direct") -> 44340 | F62: =IF(C62=0,0,C62/SUMIF(A:A,A62,C:C)) -> 0.89594546 | G62: =SUMIFS(EXPENSES!D:D, EXPENSES!F:F, Data_Consolidado!A62, EXPENSES!E:E, "Shared") -> 13055 | H62: =G62*F62 -> 11696.568 | I62: =E62+H62 -> 56036.568 | J62: =C62-I62 -> 93783.432 | K62: =IF(C62=0, "-", (J62/C62)) -> 0.62597405 | L62: =SUMIFS(Reference_Nights[[#All],[Available_nights]], Reference_Nights[[#All],[Month]], Table2[[#This Row],[Month]], Reference_Nights[[#All],[Apt]], Table2[[#This Row],[Apt]]) -> 28 | M62: =IF(Table2[[#This Row],[Available _Nights]]=0, 0, Table2[[#This Row],[Booked_Nights]]/Table2[[#This Row],[Available _Nights]]) -> 0.39285714 | N62: =IF(Table2[[#This Row],[Booked_Nights]]=0, 0, Table2[[#This Row],[Income]]/Table2[[#This Row],[Booked_Nights]]) -> 13620 | O62: =IF(L62=0,0, Table2[[#This Row],[Income]]/Table2[[#This Row],[Available _Nights]]) -> 5350.7143 | P62: =IF(Table2[[#This Row],[Income]]=0,0,Table2[[#This Row],[Total_Exp]]/Table2[[#This Row],[Income]]) -> 0.37402595
A63: 2023-11 | B63: A302 | C63: =SUMIFS(Table1[FULL AMOUNT mxn pesos], Table1[Month], A63, Table1[APARTMENT], B63) -> 41410.2 | D63: =SUMIFS(INCOME!C:C, INCOME!D:D, Table2[[#This Row],[Apt]], INCOME!J:J, Table2[[#This Row],[Month]]) -> 42 | E63: =SUMIFS(EXPENSES!$D:$D, EXPENSES!$C:$C, B63, EXPENSES!$F:$F, A63, EXPENSES!$E:$E, "Direct") -> 37800 | F63: =IF(C63=0,0,C63/SUMIF(A:A,A63,C:C)) -> 0.39420941 | G63: =SUMIFS(EXPENSES!D:D, EXPENSES!F:F, Data_Consolidado!A63, EXPENSES!E:E, "Shared") -> 5518 | H63: =G63*F63 -> 2175.2475 | I63: =E63+H63 -> 39975.247 | J63: =C63-I63 -> 1434.9525 | K63: =IF(C63=0, "-", (J63/C63)) -> 0.034652151 | L63: =SUMIFS(Reference_Nights[[#All],[Available_nights]], Reference_Nights[[#All],[Month]], Table2[[#This Row],[Month]], Reference_Nights[[#All],[Apt]], Table2[[#This Row],[Apt]]) -> 27 | M63: =IF(Table2[[#This Row],[Available _Nights]]=0, 0, Table2[[#This Row],[Booked_Nights]]/Table2[[#This Row],[Available _Nights]]) -> 1.5555556 | N63: =IF(Table2[[#This Row],[Booked_Nights]]=0, 0, Table2[[#This Row],[Income]]/Table2[[#This Row],[Booked_Nights]]) -> 985.95714 | O63: =IF(L63=0,0, Table2[[#This Row],[Income]]/Table2[[#This Row],[Available _Nights]]) -> 1533.7111 | P63: =IF(Table2[[#This Row],[Income]]=0,0,Table2[[#This Row],[Total_Exp]]/Table2[[#This Row],[Income]]) -> 0.96534785
A64: 2023-11 | B64: B303 | C64: =SUMIFS(Table1[FULL AMOUNT mxn pesos], Table1[Month], A64, Table1[APARTMENT], B64) -> 0 | D64: =SUMIFS(INCOME!C:C, INCOME!D:D, Table2[[#This Row],[Apt]], INCOME!J:J, Table2[[#This Row],[Month]]) -> 0 | E64: =SUMIFS(EXPENSES!$D:$D, EXPENSES!$C:$C, B64, EXPENSES!$F:$F, A64, EXPENSES!$E:$E, "Direct") -> 21690 | F64: =IF(C64=0,0,C64/SUMIF(A:A,A64,C:C)) -> 0 | G64: =SUMIFS(EXPENSES!D:D, EXPENSES!F:F, Data_Consolidado!A64, EXPENSES!E:E, "Shared") -> 5518 | H64: =G64*F64 -> 0 | I64: =E64+H64 -> 21690 | J64: =C64-I64 -> -21690 | K64: =IF(C64=0, "-", (J64/C64)) -> - | L64: =SUMIFS(Reference_Nights[[#All],[Available_nights]], Reference_Nights[[#All],[Month]], Table2[[#This Row],[Month]], Reference_Nights[[#All],[Apt]], Table2[[#This Row],[Apt]]) -> 27 | M64: =IF(Table2[[#This Row],[Available _Nights]]=0, 0, Table2[[#This Row],[Booked_Nights]]/Table2[[#This Row],[Available _Nights]]) -> 0 | N64: =IF(Table2[[#This Row],[Booked_Nights]]=0, 0, Table2[[#This Row],[Income]]/Table2[[#This Row],[Booked_Nights]]) -> 0 | O64: =IF(L64=0,0, Table2[[#This Row],[Income]]/Table2[[#This Row],[Available _Nights]]) -> 0 | P64: =IF(Table2[[#This Row],[Income]]=0,0,Table2[[#This Row],[Total_Exp]]/Table2[[#This Row],[Income]]) -> 0
A65: 2023-11 | B65: C301 | C65: =SUMIFS(Table1[FULL AMOUNT mxn pesos], Table1[Month], A65, Table1[APARTMENT], B65) -> 63636 | D65: =SUMIFS(INCOME!C:C, INCOME!D:D, Table2[[#This Row],[Apt]], INCOME!J:J, Table2[[#This Row],[Month]]) -> 13 | E65: =SUMIFS(EXPENSES!$D:$D, EXPENSES!$C:$C, B65, EXPENSES!$F:$F, A65, EXPENSES!$E:$E, "Direct") -> 38460 | F65: =IF(C65=0,0,C65/SUMIF(A:A,A65,C:C)) -> 0.60579059 | G65: =SUMIFS(EXPENSES!D:D, EXPENSES!F:F, Data_Consolidado!A65, EXPENSES!E:E, "Shared") -> 5518 | H65: =G65*F65 -> 3342.7525 | I65: =E65+H65 -> 41802.753 | J65: =C65-I65 -> 21833.247 | K65: =IF(C65=0, "-", (J65/C65)) -> 0.34309585 | L65: =SUMIFS(Reference_Nights[[#All],[Available_nights]], Reference_Nights[[#All],[Month]], Table2[[#This Row],[Month]], Reference_Nights[[#All],[Apt]], Table2[[#This Row],[Apt]]) -> 27 | M65: =IF(Table2[[#This Row],[Available _Nights]]=0, 0, Table2[[#This Row],[Booked_Nights]]/Table2[[#This Row],[Available _Nights]]) -> 0.48148148 | N65: =IF(Table2[[#This Row],[Booked_Nights]]=0, 0, Table2[[#This Row],[Income]]/Table2[[#This Row],[Booked_Nights]]) -> 4895.0769 | O65: =IF(L65=0,0, Table2[[#This Row],[Income]]/Table2[[#This Row],[Available _Nights]]) -> 2356.8889 | P65: =IF(Table2[[#This Row],[Income]]=0,0,Table2[[#This Row],[Total_Exp]]/Table2[[#This Row],[Income]]) -> 0.65690415
A66: 2023-12 | B66: A302 | C66: =SUMIFS(Table1[FULL AMOUNT mxn pesos], Table1[Month], A66, Table1[APARTMENT], B66) -> 132927.8 | D66: =SUMIFS(INCOME!C:C, INCOME!D:D, Table2[[#This Row],[Apt]], INCOME!J:J, Table2[[#This Row],[Month]]) -> 11 | E66: =SUMIFS(EXPENSES!$D:$D, EXPENSES!$C:$C, B66, EXPENSES!$F:$F, A66, EXPENSES!$E:$E, "Direct") -> 45360 | F66: =IF(C66=0,0,C66/SUMIF(A:A,A66,C:C)) -> 0.20586613 | G66: =SUMIFS(EXPENSES!D:D, EXPENSES!F:F, Data_Consolidado!A66, EXPENSES!E:E, "Shared") -> 1460 | H66: =G66*F66 -> 300.56455 | I66: =E66+H66 -> 45660.565 | J66: =C66-I66 -> 87267.235 | K66: =IF(C66=0, "-", (J66/C66)) -> 0.65650101 | L66: =SUMIFS(Reference_Nights[[#All],[Available_nights]], Reference_Nights[[#All],[Month]], Table2[[#This Row],[Month]], Reference_Nights[[#All],[Apt]], Table2[[#This Row],[Apt]]) -> 28 | M66: =IF(Table2[[#This Row],[Available _Nights]]=0, 0, Table2[[#This Row],[Booked_Nights]]/Table2[[#This Row],[Available _Nights]]) -> 0.39285714 | N66: =IF(Table2[[#This Row],[Booked_Nights]]=0, 0, Table2[[#This Row],[Income]]/Table2[[#This Row],[Booked_Nights]]) -> 12084.345 | O66: =IF(L66=0,0, Table2[[#This Row],[Income]]/Table2[[#This Row],[Available _Nights]]) -> 4747.4214 | P66: =IF(Table2[[#This Row],[Income]]=0,0,Table2[[#This Row],[Total_Exp]]/Table2[[#This Row],[Income]]) -> 0.34349899
A67: 2023-12 | B67: B303 | C67: =SUMIFS(Table1[FULL AMOUNT mxn pesos], Table1[Month], A67, Table1[APARTMENT], B67) -> 140103.6 | D67: =SUMIFS(INCOME!C:C, INCOME!D:D, Table2[[#This Row],[Apt]], INCOME!J:J, Table2[[#This Row],[Month]]) -> 15 | E67: =SUMIFS(EXPENSES!$D:$D, EXPENSES!$C:$C, B67, EXPENSES!$F:$F, A67, EXPENSES!$E:$E, "Direct") -> 24260 | F67: =IF(C67=0,0,C67/SUMIF(A:A,A67,C:C)) -> 0.21697933 | G67: =SUMIFS(EXPENSES!D:D, EXPENSES!F:F, Data_Consolidado!A67, EXPENSES!E:E, "Shared") -> 1460 | H67: =G67*F67 -> 316.78983 | I67: =E67+H67 -> 24576.79 | J67: =C67-I67 -> 115526.81 | K67: =IF(C67=0, "-", (J67/C67)) -> 0.82458131 | L67: =SUMIFS(Reference_Nights[[#All],[Available_nights]], Reference_Nights[[#All],[Month]], Table2[[#This Row],[Month]], Reference_Nights[[#All],[Apt]], Table2[[#This Row],[Apt]]) -> 28 | M67: =IF(Table2[[#This Row],[Available _Nights]]=0, 0, Table2[[#This Row],[Booked_Nights]]/Table2[[#This Row],[Available _Nights]]) -> 0.53571429 | N67: =IF(Table2[[#This Row],[Booked_Nights]]=0, 0, Table2[[#This Row],[Income]]/Table2[[#This Row],[Booked_Nights]]) -> 9340.24 | O67: =IF(L67=0,0, Table2[[#This Row],[Income]]/Table2[[#This Row],[Available _Nights]]) -> 5003.7 | P67: =IF(Table2[[#This Row],[Income]]=0,0,Table2[[#This Row],[Total_Exp]]/Table2[[#This Row],[Income]]) -> 0.17541869
A68: 2023-12 | B68: C301 | C68: =SUMIFS(Table1[FULL AMOUNT mxn pesos], Table1[Month], A68, Table1[APARTMENT], B68) -> 372668.8 | D68: =SUMIFS(INCOME!C:C, INCOME!D:D, Table2[[#This Row],[Apt]], INCOME!J:J, Table2[[#This Row],[Month]]) -> 42 | E68: =SUMIFS(EXPENSES!$D:$D, EXPENSES!$C:$C, B68, EXPENSES!$F:$F, A68, EXPENSES!$E:$E, "Direct") -> 39320 | F68: =IF(C68=0,0,C68/SUMIF(A:A,A68,C:C)) -> 0.57715454 | G68: =SUMIFS(EXPENSES!D:D, EXPENSES!F:F, Data_Consolidado!A68, EXPENSES!E:E, "Shared") -> 1460 | H68: =G68*F68 -> 842.64562 | I68: =E68+H68 -> 40162.646 | J68: =C68-I68 -> 332506.15 | K68: =IF(C68=0, "-", (J68/C68)) -> 0.89222965 | L68: =SUMIFS(Reference_Nights[[#All],[Available_nights]], Reference_Nights[[#All],[Month]], Table2[[#This Row],[Month]], Reference_Nights[[#All],[Apt]], Table2[[#This Row],[Apt]]) -> 28 | M68: =IF(Table2[[#This Row],[Available _Nights]]=0, 0, Table2[[#This Row],[Booked_Nights]]/Table2[[#This Row],[Available _Nights]]) -> 1.5 | N68: =IF(Table2[[#This Row],[Booked_Nights]]=0, 0, Table2[[#This Row],[Income]]/Table2[[#This Row],[Booked_Nights]]) -> 8873.0667 | O68: =IF(L68=0,0, Table2[[#This Row],[Income]]/Table2[[#This Row],[Available _Nights]]) -> 13309.6 | P68: =IF(Table2[[#This Row],[Income]]=0,0,Table2[[#This Row],[Total_Exp]]/Table2[[#This Row],[Income]]) -> 0.10777035
... A125: 2025-08 | B125: B303 | C125: =SUMIFS(Table1[FULL AMOUNT mxn pesos], Table1[Month], A125, Table1[APARTMENT], B125) -> 0 | D125: =SUMIFS(INCOME!C:C, INCOME!D:D, Table2[[#This Row],[Apt]], INCOME!J:J, Table2[[#This Row],[Month]]) -> 0 | E125: =SUMIFS(EXPENSES!$D:$D, EXPENSES!$C:$C, B125, EXPENSES!$F:$F, A125, EXPENSES!$E:$E, "Direct") -> 11000 | F125: =IF(C125=0,0,C125/SUMIF(A:A,A125,C:C)) -> 0 | G125: =SUMIFS(EXPENSES!D:D, EXPENSES!F:F, Data_Consolidado!A125, EXPENSES!E:E, "Shared") -> 1700 | H125: =G125*F125 -> 0 | I125: =E125+H125 -> 11000 | J125: =C125-I125 -> -11000 | K125: =IF(C125=0, "-", (J125/C125)) -> - | L125: =SUMIFS(Reference_Nights[[#All],[Available_nights]], Reference_Nights[[#All],[Month]], Table2[[#This Row],[Month]], Reference_Nights[[#All],[Apt]], Table2[[#This Row],[Apt]]) -> 28 | M125: =IF(Table2[[#This Row],[Available _Nights]]=0, 0, Table2[[#This Row],[Booked_Nights]]/Table2[[#This Row],[Available _Nights]]) -> 0 | N125: =IF(Table2[[#This Row],[Booked_Nights]]=0, 0, Table2[[#This Row],[Income]]/Table2[[#This Row],[Booked_Nights]]) -> 0 | O125: =IF(L125=0,0, Table2[[#This Row],[Income]]/Table2[[#This Row],[Available _Nights]]) -> 0 | P125: =IF(Table2[[#This Row],[Income]]=0,0,Table2[[#This Row],[Total_Exp]]/Table2[[#This Row],[Income]]) -> 0
A126: 2025-09 | B126: A302 | C126: =SUMIFS(Table1[FULL AMOUNT mxn pesos], Table1[Month], A126, Table1[APARTMENT], B126) -> 0 | D126: =SUMIFS(INCOME!C:C, INCOME!D:D, Table2[[#This Row],[Apt]], INCOME!J:J, Table2[[#This Row],[Month]]) -> 0 | E126: =SUMIFS(EXPENSES!$D:$D, EXPENSES!$C:$C, B126, EXPENSES!$F:$F, A126, EXPENSES!$E:$E, "Direct") -> 24662 | F126: =IF(C126=0,0,C126/SUMIF(A:A,A126,C:C)) -> 0 | G126: =SUMIFS(EXPENSES!D:D, EXPENSES!F:F, Data_Consolidado!A126, EXPENSES!E:E, "Shared") -> 5600 | H126: =Table2[[#This Row],[Shared_Total]]/2 -> 2800 | I126: =E126+H126 -> 27462 | J126: =C126-I126 -> -27462 | K126: =IF(C126=0, "-", (J126/C126)) -> - | L126: =SUMIFS(Reference_Nights[[#All],[Available_nights]], Reference_Nights[[#All],[Month]], Table2[[#This Row],[Month]], Reference_Nights[[#All],[Apt]], Table2[[#This Row],[Apt]]) -> 27 | M126: =IF(Table2[[#This Row],[Available _Nights]]=0, 0, Table2[[#This Row],[Booked_Nights]]/Table2[[#This Row],[Available _Nights]]) -> 0 | N126: =IF(Table2[[#This Row],[Booked_Nights]]=0, 0, Table2[[#This Row],[Income]]/Table2[[#This Row],[Booked_Nights]]) -> 0 | O126: =IF(L126=0,0, Table2[[#This Row],[Income]]/Table2[[#This Row],[Available _Nights]]) -> 0 | P126: =IF(Table2[[#This Row],[Income]]=0,0,Table2[[#This Row],[Total_Exp]]/Table2[[#This Row],[Income]]) -> 0
A127: 2025-09 | B127: B303 | C127: =SUMIFS(Table1[FULL AMOUNT mxn pesos], Table1[Month], A127, Table1[APARTMENT], B127) -> 0 | D127: =SUMIFS(INCOME!C:C, INCOME!D:D, Table2[[#This Row],[Apt]], INCOME!J:J, Table2[[#This Row],[Month]]) -> 0 | E127: =SUMIFS(EXPENSES!$D:$D, EXPENSES!$C:$C, B127, EXPENSES!$F:$F, A127, EXPENSES!$E:$E, "Direct") -> 11600 | F127: =IF(C127=0,0,C127/SUMIF(A:A,A127,C:C)) -> 0 | G127: =SUMIFS(EXPENSES!D:D, EXPENSES!F:F, Data_Consolidado!A127, EXPENSES!E:E, "Shared") -> 5600 | H127: =Table2[[#This Row],[Shared_Total]]/2 -> 2800 | I127: =E127+H127 -> 14400 | J127: =C127-I127 -> -14400 | K127: =IF(C127=0, "-", (J127/C127)) -> - | L127: =SUMIFS(Reference_Nights[[#All],[Available_nights]], Reference_Nights[[#All],[Month]], Table2[[#This Row],[Month]], Reference_Nights[[#All],[Apt]], Table2[[#This Row],[Apt]]) -> 27 | M127: =IF(Table2[[#This Row],[Available _Nights]]=0, 0, Table2[[#This Row],[Booked_Nights]]/Table2[[#This Row],[Available _Nights]]) -> 0 | N127: =IF(Table2[[#This Row],[Booked_Nights]]=0, 0, Table2[[#This Row],[Income]]/Table2[[#This Row],[Booked_Nights]]) -> 0 | O127: =IF(L127=0,0, Table2[[#This Row],[Income]]/Table2[[#This Row],[Available _Nights]]) -> 0 | P127: =IF(Table2[[#This Row],[Income]]=0,0,Table2[[#This Row],[Total_Exp]]/Table2[[#This Row],[Income]]) -> 0
A128: 2025-10 | B128: A302 | C128: =SUMIFS(Table1[FULL AMOUNT mxn pesos], Table1[Month], A128, Table1[APARTMENT], B128) -> 5400 | D128: =SUMIFS(INCOME!C:C, INCOME!D:D, Table2[[#This Row],[Apt]], INCOME!J:J, Table2[[#This Row],[Month]]) -> 3 | E128: =SUMIFS(EXPENSES!$D:$D, EXPENSES!$C:$C, B128, EXPENSES!$F:$F, A128, EXPENSES!$E:$E, "Direct") -> 24389 | F128: =IF(C128=0,0,C128/SUMIF(A:A,A128,C:C)) -> 1 | G128: =SUMIFS(EXPENSES!D:D, EXPENSES!F:F, Data_Consolidado!A128, EXPENSES!E:E, "Shared") -> 4000 | H128: =G128*F128 -> 4000 | I128: =E128+H128 -> 28389 | J128: =C128-I128 -> -22989 | K128: =IF(C128=0, "-", (J128/C128)) -> -4.2572222 | L128: =SUMIFS(Reference_Nights[[#All],[Available_nights]], Reference_Nights[[#All],[Month]], Table2[[#This Row],[Month]], Reference_Nights[[#All],[Apt]], Table2[[#This Row],[Apt]]) -> 28 | M128: =IF(Table2[[#This Row],[Available _Nights]]=0, 0, Table2[[#This Row],[Booked_Nights]]/Table2[[#This Row],[Available _Nights]]) -> 0.10714286 | N128: =IF(Table2[[#This Row],[Booked_Nights]]=0, 0, Table2[[#This Row],[Income]]/Table2[[#This Row],[Booked_Nights]]) -> 1800 | O128: =IF(L128=0,0, Table2[[#This Row],[Income]]/Table2[[#This Row],[Available _Nights]]) -> 192.85714 | P128: =IF(Table2[[#This Row],[Income]]=0,0,Table2[[#This Row],[Total_Exp]]/Table2[[#This Row],[Income]]) -> 5.2572222
A129: 2025-10 | B129: B303 | C129: =SUMIFS(Table1[FULL AMOUNT mxn pesos], Table1[Month], A129, Table1[APARTMENT], B129) -> 0 | D129: =SUMIFS(INCOME!C:C, INCOME!D:D, Table2[[#This Row],[Apt]], INCOME!J:J, Table2[[#This Row],[Month]]) -> 0 | E129: =SUMIFS(EXPENSES!$D:$D, EXPENSES!$C:$C, B129, EXPENSES!$F:$F, A129, EXPENSES!$E:$E, "Direct") -> 12500 | F129: =IF(C129=0,0,C129/SUMIF(A:A,A129,C:C)) -> 0 | G129: =SUMIFS(EXPENSES!D:D, EXPENSES!F:F, Data_Consolidado!A129, EXPENSES!E:E, "Shared") -> 4000 | H129: =G129*F129 -> 0 | I129: =E129+H129 -> 12500 | J129: =C129-I129 -> -12500 | K129: =IF(C129=0, "-", (J129/C129)) -> - | L129: =SUMIFS(Reference_Nights[[#All],[Available_nights]], Reference_Nights[[#All],[Month]], Table2[[#This Row],[Month]], Reference_Nights[[#All],[Apt]], Table2[[#This Row],[Apt]]) -> 28 | M129: =IF(Table2[[#This Row],[Available _Nights]]=0, 0, Table2[[#This Row],[Booked_Nights]]/Table2[[#This Row],[Available _Nights]]) -> 0 | N129: =IF(Table2[[#This Row],[Booked_Nights]]=0, 0, Table2[[#This Row],[Income]]/Table2[[#This Row],[Booked_Nights]]) -> 0 | O129: =IF(L129=0,0, Table2[[#This Row],[Income]]/Table2[[#This Row],[Available _Nights]]) -> 0 | P129: =IF(Table2[[#This Row],[Income]]=0,0,Table2[[#This Row],[Total_Exp]]/Table2[[#This Row],[Income]]) -> 0
A130: 2025-11 | B130: A302 | C130: =SUMIFS(Table1[FULL AMOUNT mxn pesos], Table1[Month], A130, Table1[APARTMENT], B130) -> 48000 | D130: =SUMIFS(INCOME!C:C, INCOME!D:D, Table2[[#This Row],[Apt]], INCOME!J:J, Table2[[#This Row],[Month]]) -> 21 | E130: =SUMIFS(EXPENSES!$D:$D, EXPENSES!$C:$C, B130, EXPENSES!$F:$F, A130, EXPENSES!$E:$E, "Direct") -> 24141 | F130: =IF(C130=0,0,C130/SUMIF(A:A,A130,C:C)) -> 1 | G130: =SUMIFS(EXPENSES!D:D, EXPENSES!F:F, Data_Consolidado!A130, EXPENSES!E:E, "Shared") -> 500 | H130: =G130*F130 -> 500 | I130: =E130+H130 -> 24641 | J130: =C130-I130 -> 23359 | K130: =IF(C130=0, "-", (J130/C130)) -> 0.48664583 | L130: =SUMIFS(Reference_Nights[[#All],[Available_nights]], Reference_Nights[[#All],[Month]], Table2[[#This Row],[Month]], Reference_Nights[[#All],[Apt]], Table2[[#This Row],[Apt]]) -> 27 | M130: =IF(Table2[[#This Row],[Available _Nights]]=0, 0, Table2[[#This Row],[Booked_Nights]]/Table2[[#This Row],[Available _Nights]]) -> 0.77777778 | N130: =IF(Table2[[#This Row],[Booked_Nights]]=0, 0, Table2[[#This Row],[Income]]/Table2[[#This Row],[Booked_Nights]]) -> 2285.7143 | O130: =IF(L130=0,0, Table2[[#This Row],[Income]]/Table2[[#This Row],[Available _Nights]]) -> 1777.7778 | P130: =IF(Table2[[#This Row],[Income]]=0,0,Table2[[#This Row],[Total_Exp]]/Table2[[#This Row],[Income]]) -> 0.51335417
A131: 2025-11 | B131: B303 | C131: =SUMIFS(Table1[FULL AMOUNT mxn pesos], Table1[Month], A131, Table1[APARTMENT], B131) -> 0 | D131: =SUMIFS(INCOME!C:C, INCOME!D:D, Table2[[#This Row],[Apt]], INCOME!J:J, Table2[[#This Row],[Month]]) -> 0 | E131: =SUMIFS(EXPENSES!$D:$D, EXPENSES!$C:$C, B131, EXPENSES!$F:$F, A131, EXPENSES!$E:$E, "Direct") -> 14400 | F131: =IF(C131=0,0,C131/SUMIF(A:A,A131,C:C)) -> 0 | G131: =SUMIFS(EXPENSES!D:D, EXPENSES!F:F, Data_Consolidado!A131, EXPENSES!E:E, "Shared") -> 500 | H131: =G131*F131 -> 0 | I131: =E131+H131 -> 14400 | J131: =C131-I131 -> -14400 | K131: =IF(C131=0, "-", (J131/C131)) -> - | L131: =SUMIFS(Reference_Nights[[#All],[Available_nights]], Reference_Nights[[#All],[Month]], Table2[[#This Row],[Month]], Reference_Nights[[#All],[Apt]], Table2[[#This Row],[Apt]]) -> 27 | M131: =IF(Table2[[#This Row],[Available _Nights]]=0, 0, Table2[[#This Row],[Booked_Nights]]/Table2[[#This Row],[Available _Nights]]) -> 0 | N131: =IF(Table2[[#This Row],[Booked_Nights]]=0, 0, Table2[[#This Row],[Income]]/Table2[[#This Row],[Booked_Nights]]) -> 0 | O131: =IF(L131=0,0, Table2[[#This Row],[Income]]/Table2[[#This Row],[Available _Nights]]) -> 0 | P131: =IF(Table2[[#This Row],[Income]]=0,0,Table2[[#This Row],[Total_Exp]]/Table2[[#This Row],[Income]]) -> 0
A132: 2025-12 | B132: A302 | C132: =SUMIFS(Table1[FULL AMOUNT mxn pesos], Table1[Month], A132, Table1[APARTMENT], B132) -> 9100 | D132: =SUMIFS(INCOME!C:C, INCOME!D:D, Table2[[#This Row],[Apt]], INCOME!J:J, Table2[[#This Row],[Month]]) -> 3 | E132: =SUMIFS(EXPENSES!$D:$D, EXPENSES!$C:$C, B132, EXPENSES!$F:$F, A132, EXPENSES!$E:$E, "Direct") -> 26707 | F132: =IF(C132=0,0,C132/SUMIF(A:A,A132,C:C)) -> 0.16221034 | G132: =SUMIFS(EXPENSES!D:D, EXPENSES!F:F, Data_Consolidado!A132, EXPENSES!E:E, "Shared") -> 21580 | H132: =G132*F132 -> 3500.4991 | I132: =E132+H132 -> 30207.499 | J132: =C132-I132 -> -21107.499 | K132: =IF(C132=0, "-", (J132/C132)) -> -2.3195054 | L132: =SUMIFS(Reference_Nights[[#All],[Available_nights]], Reference_Nights[[#All],[Month]], Table2[[#This Row],[Month]], Reference_Nights[[#All],[Apt]], Table2[[#This Row],[Apt]]) -> 28 | M132: =IF(Table2[[#This Row],[Available _Nights]]=0, 0, Table2[[#This Row],[Booked_Nights]]/Table2[[#This Row],[Available _Nights]]) -> 0.10714286 | N132: =IF(Table2[[#This Row],[Booked_Nights]]=0, 0, Table2[[#This Row],[Income]]/Table2[[#This Row],[Booked_Nights]]) -> 3033.3333 | O132: =IF(L132=0,0, Table2[[#This Row],[Income]]/Table2[[#This Row],[Available _Nights]]) -> 325 | P132: =IF(Table2[[#This Row],[Income]]=0,0,Table2[[#This Row],[Total_Exp]]/Table2[[#This Row],[Income]]) -> 3.3195054
A133: 2025-12 | B133: B303 | C133: =SUMIFS(Table1[FULL AMOUNT mxn pesos], Table1[Month], A133, Table1[APARTMENT], B133) -> 47000 | D133: =SUMIFS(INCOME!C:C, INCOME!D:D, Table2[[#This Row],[Apt]], INCOME!J:J, Table2[[#This Row],[Month]]) -> 11 | E133: =SUMIFS(EXPENSES!$D:$D, EXPENSES!$C:$C, B133, EXPENSES!$F:$F, A133, EXPENSES!$E:$E, "Direct") -> 15200 | F133: =IF(C133=0,0,C133/SUMIF(A:A,A133,C:C)) -> 0.83778966 | G133: =SUMIFS(EXPENSES!D:D, EXPENSES!F:F, Data_Consolidado!A133, EXPENSES!E:E, "Shared") -> 21580 | H133: =G133*F133 -> 18079.501 | I133: =E133+H133 -> 33279.501 | J133: =C133-I133 -> 13720.499 | K133: =IF(C133=0, "-", (J133/C133)) -> 0.29192551 | L133: =SUMIFS(Reference_Nights[[#All],[Available_nights]], Reference_Nights[[#All],[Month]], Table2[[#This Row],[Month]], Reference_Nights[[#All],[Apt]], Table2[[#This Row],[Apt]]) -> 28 | M133: =IF(Table2[[#This Row],[Available _Nights]]=0, 0, Table2[[#This Row],[Booked_Nights]]/Table2[[#This Row],[Available _Nights]]) -> 0.39285714 | N133: =IF(Table2[[#This Row],[Booked_Nights]]=0, 0, Table2[[#This Row],[Income]]/Table2[[#This Row],[Booked_Nights]]) -> 4272.7273 | O133: =IF(L133=0,0, Table2[[#This Row],[Income]]/Table2[[#This Row],[Available _Nights]]) -> 1678.5714 | P133: =IF(Table2[[#This Row],[Income]]=0,0,Table2[[#This Row],[Total_Exp]]/Table2[[#This Row],[Income]]) -> 0.70807449
A134: 2026-01 | B134: A302 | C134: =SUMIFS(Table1[FULL AMOUNT mxn pesos], Table1[Month], A134, Table1[APARTMENT], B134) -> 53519.8 | D134: =SUMIFS(INCOME!C:C, INCOME!D:D, Table2[[#This Row],[Apt]], INCOME!J:J, Table2[[#This Row],[Month]]) -> 24 | E134: =SUMIFS(EXPENSES!$D:$D, EXPENSES!$C:$C, B134, EXPENSES!$F:$F, A134, EXPENSES!$E:$E, "Direct") -> 40258 | F134: =IF(C134=0,0,C134/SUMIF(A:A,A134,C:C)) -> 0.46035528 | G134: =SUMIFS(EXPENSES!D:D, EXPENSES!F:F, Data_Consolidado!A134, EXPENSES!E:E, "Shared") -> 9950 | H134: =G134*F134 -> 4580.535 | I134: =E134+H134 -> 44838.535 | J134: =C134-I134 -> 8681.265 | K134: =IF(C134=0, "-", (J134/C134)) -> 0.1622066 | L134: =SUMIFS(Reference_Nights[[#All],[Available_nights]], Reference_Nights[[#All],[Month]], Table2[[#This Row],[Month]], Reference_Nights[[#All],[Apt]], Table2[[#This Row],[Apt]]) -> 28 | M134: =IF(Table2[[#This Row],[Available _Nights]]=0, 0, Table2[[#This Row],[Booked_Nights]]/Table2[[#This Row],[Available _Nights]]) -> 0.85714286 | N134: =IF(Table2[[#This Row],[Booked_Nights]]=0, 0, Table2[[#This Row],[Income]]/Table2[[#This Row],[Booked_Nights]]) -> 2229.9917 | O134: =IF(L134=0,0, Table2[[#This Row],[Income]]/Table2[[#This Row],[Available _Nights]]) -> 1911.4214 | P134: =IF(Table2[[#This Row],[Income]]=0,0,Table2[[#This Row],[Total_Exp]]/Table2[[#This Row],[Income]]) -> 0.8377934
A135: 2026-01 | B135: B303 | C135: =SUMIFS(Table1[FULL AMOUNT mxn pesos], Table1[Month], A135, Table1[APARTMENT], B135) -> 62737.8 | D135: =SUMIFS(INCOME!C:C, INCOME!D:D, Table2[[#This Row],[Apt]], INCOME!J:J, Table2[[#This Row],[Month]]) -> 19 | E135: =SUMIFS(EXPENSES!$D:$D, EXPENSES!$C:$C, B135, EXPENSES!$F:$F, A135, EXPENSES!$E:$E, "Direct") -> 18265 | F135: =IF(C135=0,0,C135/SUMIF(A:A,A135,C:C)) -> 0.53964472 | G135: =SUMIFS(EXPENSES!D:D, EXPENSES!F:F, Data_Consolidado!A135, EXPENSES!E:E, "Shared") -> 9950 | H135: =G135*F135 -> 5369.465 | I135: =E135+H135 -> 23634.465 | J135: =C135-I135 -> 39103.335 | K135: =IF(C135=0, "-", (J135/C135)) -> 0.6232819 | L135: =SUMIFS(Reference_Nights[[#All],[Available_nights]], Reference_Nights[[#All],[Month]], Table2[[#This Row],[Month]], Reference_Nights[[#All],[Apt]], Table2[[#This Row],[Apt]]) -> 28 | M135: =IF(Table2[[#This Row],[Available _Nights]]=0, 0, Table2[[#This Row],[Booked_Nights]]/Table2[[#This Row],[Available _Nights]]) -> 0.67857143 | N135: =IF(Table2[[#This Row],[Booked_Nights]]=0, 0, Table2[[#This Row],[Income]]/Table2[[#This Row],[Booked_Nights]]) -> 3301.9895 | O135: =IF(L135=0,0, Table2[[#This Row],[Income]]/Table2[[#This Row],[Available _Nights]]) -> 2240.6357 | P135: =IF(Table2[[#This Row],[Income]]=0,0,Table2[[#This Row],[Total_Exp]]/Table2[[#This Row],[Income]]) -> 0.3767181
A136: 2026-02 | B136: A302 | C136: =SUMIFS(Table1[FULL AMOUNT mxn pesos], Table1[Month], A136, Table1[APARTMENT], B136) -> 33216.4 | D136: =SUMIFS(INCOME!C:C, INCOME!D:D, Table2[[#This Row],[Apt]], INCOME!J:J, Table2[[#This Row],[Month]]) -> 21 | E136: =SUMIFS(EXPENSES!$D:$D, EXPENSES!$C:$C, B136, EXPENSES!$F:$F, A136, EXPENSES!$E:$E, "Direct") -> 36757 | F136: =IF(C136=0,0,C136/SUMIF(A:A,A136,C:C)) -> 1 | G136: =SUMIFS(EXPENSES!D:D, EXPENSES!F:F, Data_Consolidado!A136, EXPENSES!E:E, "Shared") -> 20080 | H136: =G136*F136 -> 20080 | I136: =E136+H136 -> 56837 | J136: =C136-I136 -> -23620.6 | K136: =IF(C136=0, "-", (J136/C136)) -> -0.71111258 | L136: =SUMIFS(Reference_Nights[[#All],[Available_nights]], Reference_Nights[[#All],[Month]], Table2[[#This Row],[Month]], Reference_Nights[[#All],[Apt]], Table2[[#This Row],[Apt]]) -> 25 | M136: =IF(Table2[[#This Row],[Available _Nights]]=0, 0, Table2[[#This Row],[Booked_Nights]]/Table2[[#This Row],[Available _Nights]]) -> 0.84 | N136: =IF(Table2[[#This Row],[Booked_Nights]]=0, 0, Table2[[#This Row],[Income]]/Table2[[#This Row],[Booked_Nights]]) -> 1581.7333 | O136: =IF(L136=0,0, Table2[[#This Row],[Income]]/Table2[[#This Row],[Available _Nights]]) -> 1328.656 | P136: =IF(Table2[[#This Row],[Income]]=0,0,Table2[[#This Row],[Total_Exp]]/Table2[[#This Row],[Income]]) -> 1.7111126
A137: 2026-02 | B137: B303 | C137: =SUMIFS(Table1[FULL AMOUNT mxn pesos], Table1[Month], A137, Table1[APARTMENT], B137) -> 0 | D137: =SUMIFS(INCOME!C:C, INCOME!D:D, Table2[[#This Row],[Apt]], INCOME!J:J, Table2[[#This Row],[Month]]) -> 0 | E137: =SUMIFS(EXPENSES!$D:$D, EXPENSES!$C:$C, B137, EXPENSES!$F:$F, A137, EXPENSES!$E:$E, "Direct") -> 14000 | F137: =IF(C137=0,0,C137/SUMIF(A:A,A137,C:C)) -> 0 | G137: =SUMIFS(EXPENSES!D:D, EXPENSES!F:F, Data_Consolidado!A137, EXPENSES!E:E, "Shared") -> 20080 | H137: =G137*F137 -> 0 | I137: =E137+H137 -> 14000 | J137: =C137-I137 -> -14000 | K137: =IF(C137=0, "-", (J137/C137)) -> - | L137: =SUMIFS(Reference_Nights[[#All],[Available_nights]], Reference_Nights[[#All],[Month]], Table2[[#This Row],[Month]], Reference_Nights[[#All],[Apt]], Table2[[#This Row],[Apt]]) -> 25 | M137: =IF(Table2[[#This Row],[Available _Nights]]=0, 0, Table2[[#This Row],[Booked_Nights]]/Table2[[#This Row],[Available _Nights]]) -> 0 | N137: =IF(Table2[[#This Row],[Booked_Nights]]=0, 0, Table2[[#This Row],[Income]]/Table2[[#This Row],[Booked_Nights]]) -> 0 | O137: =IF(L137=0,0, Table2[[#This Row],[Income]]/Table2[[#This Row],[Available _Nights]]) -> 0 | P137: =IF(Table2[[#This Row],[Income]]=0,0,Table2[[#This Row],[Total_Exp]]/Table2[[#This Row],[Income]]) -> 0
A138: 2026-03 | B138: A302 | C138: =SUMIFS(Table1[FULL AMOUNT mxn pesos], Table1[Month], A138, Table1[APARTMENT], B138) -> 19460 | D138: =SUMIFS(INCOME!C:C, INCOME!D:D, Table2[[#This Row],[Apt]], INCOME!J:J, Table2[[#This Row],[Month]]) -> 12 | E138: =SUMIFS(EXPENSES!$D:$D, EXPENSES!$C:$C, B138, EXPENSES!$F:$F, A138, EXPENSES!$E:$E, "Direct") -> 43442 | F138: =IF(C138=0,0,C138/SUMIF(A:A,A138,C:C)) -> 1 | G138: =SUMIFS(EXPENSES!D:D, EXPENSES!F:F, Data_Consolidado!A138, EXPENSES!E:E, "Shared") -> 5970 | H138: =G138*F138 -> 5970 | I138: =E138+H138 -> 49412 | J138: =C138-I138 -> -29952 | K138: =IF(C138=0, "-", (J138/C138)) -> -1.5391572 | L138: =SUMIFS(Reference_Nights[[#All],[Available_nights]], Reference_Nights[[#All],[Month]], Table2[[#This Row],[Month]], Reference_Nights[[#All],[Apt]], Table2[[#This Row],[Apt]]) -> 28 | M138: =IF(Table2[[#This Row],[Available _Nights]]=0, 0, Table2[[#This Row],[Booked_Nights]]/Table2[[#This Row],[Available _Nights]]) -> 0.42857143 | N138: =IF(Table2[[#This Row],[Booked_Nights]]=0, 0, Table2[[#This Row],[Income]]/Table2[[#This Row],[Booked_Nights]]) -> 1621.6667 | O138: =IF(L138=0,0, Table2[[#This Row],[Income]]/Table2[[#This Row],[Available _Nights]]) -> 695 | P138: =IF(Table2[[#This Row],[Income]]=0,0,Table2[[#This Row],[Total_Exp]]/Table2[[#This Row],[Income]]) -> 2.5391572
A139: 2026-03 | B139: B303 | C139: =SUMIFS(Table1[FULL AMOUNT mxn pesos], Table1[Month], A139, Table1[APARTMENT], B139) -> 0 | D139: =SUMIFS(INCOME!C:C, INCOME!D:D, Table2[[#This Row],[Apt]], INCOME!J:J, Table2[[#This Row],[Month]]) -> 0 | E139: =SUMIFS(EXPENSES!$D:$D, EXPENSES!$C:$C, B139, EXPENSES!$F:$F, A139, EXPENSES!$E:$E, "Direct") -> 11000 | F139: =IF(C139=0,0,C139/SUMIF(A:A,A139,C:C)) -> 0 | G139: =SUMIFS(EXPENSES!D:D, EXPENSES!F:F, Data_Consolidado!A139, EXPENSES!E:E, "Shared") -> 5970 | H139: =G139*F139 -> 0 | I139: =E139+H139 -> 11000 | J139: =C139-I139 -> -11000 | K139: =IF(C139=0, "-", (J139/C139)) -> - | L139: =SUMIFS(Reference_Nights[[#All],[Available_nights]], Reference_Nights[[#All],[Month]], Table2[[#This Row],[Month]], Reference_Nights[[#All],[Apt]], Table2[[#This Row],[Apt]]) -> 28 | M139: =IF(Table2[[#This Row],[Available _Nights]]=0, 0, Table2[[#This Row],[Booked_Nights]]/Table2[[#This Row],[Available _Nights]]) -> 0 | N139: =IF(Table2[[#This Row],[Booked_Nights]]=0, 0, Table2[[#This Row],[Income]]/Table2[[#This Row],[Booked_Nights]]) -> 0 | O139: =IF(L139=0,0, Table2[[#This Row],[Income]]/Table2[[#This Row],[Available _Nights]]) -> 0 | P139: =IF(Table2[[#This Row],[Income]]=0,0,Table2[[#This Row],[Total_Exp]]/Table2[[#This Row],[Income]]) -> 0
... A143: 2026-05 | B143: B303 | C143: =SUMIFS(Table1[FULL AMOUNT mxn pesos], Table1[Month], A143, Table1[APARTMENT], B143) -> 0 | D143: =SUMIFS(INCOME!C:C, INCOME!D:D, Table2[[#This Row],[Apt]], INCOME!J:J, Table2[[#This Row],[Month]]) -> 0 | E143: =SUMIFS(EXPENSES!$D:$D, EXPENSES!$C:$C, B143, EXPENSES!$F:$F, A143, EXPENSES!$E:$E, "Direct") -> 13200 | F143: =IF(C143=0,0,C143/SUMIF(A:A,A143,C:C)) -> 0 | G143: =SUMIFS(EXPENSES!D:D, EXPENSES!F:F, Data_Consolidado!A143, EXPENSES!E:E, "Shared") -> 0 | H143: =G143*F143 -> 0 | I143: =E143+H143 -> 13200 | J143: =C143-I143 -> -13200 | K143: =IF(C143=0, "-", (J143/C143)) -> - | L143: =SUMIFS(Reference_Nights[[#All],[Available_nights]], Reference_Nights[[#All],[Month]], Table2[[#This Row],[Month]], Reference_Nights[[#All],[Apt]], Table2[[#This Row],[Apt]]) -> 28 | M143: =IF(Table2[[#This Row],[Available _Nights]]=0, 0, Table2[[#This Row],[Booked_Nights]]/Table2[[#This Row],[Available _Nights]]) -> 0 | N143: =IF(Table2[[#This Row],[Booked_Nights]]=0, 0, Table2[[#This Row],[Income]]/Table2[[#This Row],[Booked_Nights]]) -> 0 | O143: =IF(L143=0,0, Table2[[#This Row],[Income]]/Table2[[#This Row],[Available _Nights]]) -> 0 | P143: =IF(Table2[[#This Row],[Income]]=0,0,Table2[[#This Row],[Total_Exp]]/Table2[[#This Row],[Income]]) -> 0

Sheet Analysis - Pivots
B4: CORE KPIs
B6: Total_Profit
B8: Total_Profit
B9: 169615.83
B28: Margin_Total %
B30: Sum of Total_Margin %
B31: 0.14448702
B50: Avg_Occupancy_Rate
B52: Avg_Occupancy_Rate
B53: 0.37709609
B70: Avg_ADR
B72: Avg_ADR
B73: 2743.1385
B90: TRENDS
B92: Profit_by_Year
B94: Year | C94: Total_Profit
B95: 2022 | C95: 115284.95
B96: 2023 | C96: 130131.33
B97: 2024 | C97: -13784.47
B98: 2025 | C98: -51319.31
B99: 2026 | C99: -10696.665
B116: Occupancy_by_Year
B118: Year | C118: Avg_Occupancy_Rate
B119: 2022 | C119: 0.41236772
B120: 2023 | C120: 0.26178131
B121: 2024 | C121: 0.74392043
B122: 2025 | C122: 0.19089065
B123: 2026 | C123: 0.13571429
B133: BREAKDOWNS
B135: Income by Rental Platform
B137: Income | C137: Rental_Platform
B138: Year | C138: Airbnb | D138: Booking | E138: Direct Reservation | F138: Expedia | G138: Google | H138: Intima Reservation | I138: Lodgify | J138: VRBO
B139: 2022 | C139: 649674.8 | D139: 8960 | E139: 9442.4 | F139: 114747
B140: 2023 | C140: 998953.6 | D140: 7516.2 | E140: 479052 | F140: 373045.8 | G140: 7211.4 | H140: 32994.8
B141: 2024 | C141: 570102 | D141: 93218.6 | E141: 266332.8 | F141: 836557.8 | I141: 47752 | J141: 16261
B142: 2025 | C142: 300440.4 | D142: 11753.8 | E142: 72287 | F142: 144813.6 | I142: 20660.2
B143: 2026 | C143: 124731.2 | D143: 11462.8 | E143: 25220 | F143: 55700
J188: Apt_Comparison
J190: Apt | K190: Profit_Total | L190: Avg_Occupancy_Rate | M190: Avg_ADR | N190: Avg_RevPAN
J191: A302 | K191: 570535.16 | L191: 0.45908256 | M191: 2737.5262 | N191: 1529.1668
J192: B303 | K192: 169615.83 | L192: 0.37709609 | M192: 2743.1385 | N192: 808.44193
J193: C301 | K193: 751376.91 | L193: 0.6548242 | M193: 2454.9351 | N193: 1884.6358

Sheet Analysis - Dashboard
C2: VACATION RENTAL PERFORMANCE DASHBOARD (2022-2026)
